desc_lib.v
// Design of encoder for inputs ~ makes use of Behavioural Description
module input_encoder (input [9:0] D_in, output reg [4:0] BCD_out);

    always @(D_in) begin
        casez (D_in)
            10'b0000000001: BCD_out = 5'b10000;  // D_in[0]
            10'b000000001?: BCD_out = 5'b10001;  // D_in[1]
            10'b00000001??: BCD_out = 5'b10010;  // D_in[2]
            10'b0000001???: BCD_out = 5'b10011;  // D_in[3]
            10'b000001????: BCD_out = 5'b10100;  // D_in[4]
            10'b00001?????: BCD_out = 5'b10101;  // D_in[5]
            10'b0001??????: BCD_out = 5'b10110;  // D_in[6]
            10'b001???????: BCD_out = 5'b10111;  // D_in[7]
            10'b01????????: BCD_out = 5'b11000;  // D_in[8]
            10'b1?????????: BCD_out = 5'b11001;  // D_in[9]
            default: BCD_out = 5'b00000;  // Default case to handle no-input states
        endcase

    end

endmodule

// Design of 1-2 Demultiplexer for clocking T flip-flops - makes use of Behavioural Description
module demux1_2 (output reg [1:0] Mode_out, input Press_in, input select);

    always @(Press_in, select) begin
        Mode_out = 2'b00;
        case (select)
            1'b0: Mode_out[0] = Press_in;
            1'b1: Mode_out[1] = Press_in;
            default: Mode_out = 2'b00;
        endcase
    end

endmodule

// Design of a T flipflops for clocking the memory for inputs sequentially - makes use of Behavioural Description
module t_ff (output reg q, output qbar, input clk, rst, t);

	assign qbar = ~q;

	always @(posedge clk)
	begin
		if (rst)
			q <= 0;
		else
			case(t)
				1'b0: q <= q;
				1'b1: q <= ~q;
			endcase
	end

    always @(negedge clk)
    begin
        if (rst)
			q <= 0;
    end
endmodule

// Design of a T-FF circuit ~ makes use of Gate-Level Modelling
module t_ff_circuit (output wire q1, q2, q3, qbar1, qbar2, qbar3, input clk, rst, t);

    wire t1_q, t1_qbar;
    
    t_ff t1 (t1_q, t1_qbar, clk, rst, t);
    
    t_ff t2 (q2, qbar2, t1_q, rst, t);

    t_ff t3 (q3, qbar3, t1_qbar, rst, t);
    
    assign q1 = t1_q;
    assign qbar1 = t1_qbar;

endmodule

module t_ff_circuit_upscaled (output wire q1, q2, q3, q4, q5, q6, q7,
    qbar1, qbar2, qbar3, qbar4, qbar5, qbar6, qbar7, input clk, rst, t);

    wire t1_q, t1_qbar, t2_q, t2_qbar, t3_q, t3_qbar;

    t_ff t1 (t1_q, t1_qbar, clk, rst, t);

    t_ff t2 (t2_q, t2_qbar, t1_q, rst, t);

    t_ff t3 (t3_q, t3_qbar, t1_qbar, rst, t);
    
    t_ff t4 (q4, qbar4, t2_q, rst, t);

    t_ff t5 (q5, qbar5, t2_qbar, rst, t);

    t_ff t6 (q6, qbar6, t3_q, rst, t);

    t_ff t7 (q7, qbar7, t3_qbar, rst, t);

    assign q1 = t1_q;
    assign qbar1 = t1_qbar;
    assign q2 = t2_q;
    assign qbar2 = t2_qbar;
    assign q3 = t3_q;
    assign qbar3 = t3_qbar;
    
endmodule

module univ_shift_reg (output reg [3:0] reg_out, input clock, reset, input [1:0] reg_mode, input [3:0] reg_in);

    always @(reset) begin
        case (reset)
            1'b1: reg_out = 4'b0000;
            default: reg_out = reg_out;
        endcase
    end

    always @(posedge clock)
    begin
        if(reset)
        reg_out <= 4'b0000;
        else
        begin
            case(reg_mode)
            2'b00 : reg_out <= reg_out;      // locked mode, do nothing
            2'b01 : reg_out <= {reg_in[0], reg_out[3:1]};//reg_out >> 1; // RFSR
            2'b10 : reg_out <= {reg_out[2:0], reg_in[0]};//reg_out << 1; // LFSR
            2'b11 : reg_out <= reg_in;       // parallel in parallel out
            endcase
        end
    end
  
endmodule

module shift_reg_array (input clk1, clk2, clk3, clk4, clear,
    input [3:0] reg_in1, input [3:0] reg_in2, input [3:0] reg_in3, input [3:0] reg_in4, input [1:0] reg_mode, 
    output [3:0] reg_out1, output [3:0] reg_out2, output [3:0] reg_out3, output [3:0] reg_out4);

    univ_shift_reg reg1(reg_out1, clk1, clear, reg_mode, reg_in1);
    univ_shift_reg reg2(reg_out2, clk2, clear, reg_mode, reg_in2);
    univ_shift_reg reg3(reg_out3, clk3, clear, reg_mode, reg_in3);
    univ_shift_reg reg4(reg_out4, clk4, clear, reg_mode, reg_in4);

endmodule

module shift_reg_array_upscaled (input clk1, clk2, clk3, clk4, clk5, clk6, clear,
    input [3:0] reg_in1, input [3:0] reg_in2, input [3:0] reg_in3, input [3:0] reg_in4, input [3:0] reg_in5, input [3:0] reg_in6, input [1:0] reg_mode, 
    output [3:0] reg_out1, output [3:0] reg_out2, output [3:0] reg_out3, output [3:0] reg_out4, output [3:0] reg_out5, output [3:0] reg_out6);

    univ_shift_reg reg1(reg_out1, clk1, clear, reg_mode, reg_in1);
    univ_shift_reg reg2(reg_out2, clk2, clear, reg_mode, reg_in2);
    univ_shift_reg reg3(reg_out3, clk3, clear, reg_mode, reg_in3);
    univ_shift_reg reg4(reg_out4, clk4, clear, reg_mode, reg_in4);
    univ_shift_reg reg5(reg_out5, clk5, clear, reg_mode, reg_in5);
    univ_shift_reg reg6(reg_out6, clk6, clear, reg_mode, reg_in6);

endmodule

main_tb_upscaled.v
`timescale 1 ns / 1 ns
`include "desc_lib.v"

module main_tb;

    wire [4:0] out;
    wire [1:0] mode_out;
    wire [3:0] reg_out1, reg_out2, reg_out3, reg_out4, reg_out5, reg_out6;
    reg [9:0] x;
    reg sel, rst_ui, t;
    wire q1_ui, q2_ui, q3_ui, q4_ui, q5_ui, q6_ui, q7_ui, qbar1_ui, qbar2_ui, qbar3_ui, qbar4_ui, qbar5_ui, qbar6_ui, qbar7_ui;

    input_encoder enc(x, out);
    demux1_2 dmx(mode_out, out[4], sel);
    t_ff_circuit_upscaled input_t_ff(q1_ui, q2_ui, q3_ui, q4_ui, q5_ui, q6_ui, q7_ui, qbar1_ui, qbar2_ui, qbar3_ui, qbar4_ui, qbar5_ui, qbar6_ui, qbar7_ui, mode_out[0], rst_ui, t);
    shift_reg_array_upscaled input_array(q4_ui, q6_ui, q5_ui, q7_ui, qbar4_ui, qbar6_ui, rst_ui, out[3:0], out[3:0], out[3:0], out[3:0], out[3:0], out[3:0], 2'b11,
        reg_out1, reg_out2, reg_out3, reg_out4, reg_out5, reg_out6);

    /*
    initial begin
        clk = 0;
        forever #5 clk = ~clk;
    end
    */

    initial begin
        $dumpfile("main_tb.vcd"); $dumpvars(0, main_tb);

        $display("*** SIMULATING INPUT ENCODER ***");
        $display("\t BCD Output\t   Keypad Input\t    Demux Output\t\t     TFF Output\t\t\t\t\t       Shift Register Output");
        $monitor("\t   %b\t    %b\t         %b\t\t     clk1=%b, clk2=%b, clk3=%b, clk4=%b, clk5=%b, clk6=%b\t\t       SR1=%b, SR2=%b, SR3=%b, SR4=%b, SR5=%b, SR6=%b", out, x, mode_out, q4_ui, q6_ui, q5_ui, q7_ui, qbar4_ui, qbar6_ui, reg_out1, reg_out2, reg_out3, reg_out4, reg_out5, reg_out6);

        x[0]=0; x[1]=0; x[2]=0; x[3]=0; x[4]=0; 
        x[5]=0; x[6]=0; x[7]=0; x[8]=0; x[9]=0;

        sel = 0;
        t = 0;
        rst_ui = 1;
        
        
        #1 t = 1;
        #1 rst_ui = 0;
        #5 x[2]=1;
        #5 x[2]=0;
        #5 x[1]=1;
        #5 x[1]=0;
        #5 x[9]=1;
        #5 x[9]=0;
        #5 x[3]=1;
        #5 x[3]=0;
        #5 x[5]=1;
        #5 x[5]=0;
        #5 x[4]=1;
        #5 x[4]=0;
        #20 $finish;

    end


endmodule

main_tb.vcd
$date
	Tue Jul 16 17:21:23 2024
$end
$version
	Icarus Verilog
$end
$timescale
	1ns
$end
$scope module main_tb $end
$var wire 4 ! reg_out6 [3:0] $end
$var wire 4 " reg_out5 [3:0] $end
$var wire 4 # reg_out4 [3:0] $end
$var wire 4 $ reg_out3 [3:0] $end
$var wire 4 % reg_out2 [3:0] $end
$var wire 4 & reg_out1 [3:0] $end
$var wire 1 ' qbar7_ui $end
$var wire 1 ( qbar6_ui $end
$var wire 1 ) qbar5_ui $end
$var wire 1 * qbar4_ui $end
$var wire 1 + qbar3_ui $end
$var wire 1 , qbar2_ui $end
$var wire 1 - qbar1_ui $end
$var wire 1 . q7_ui $end
$var wire 1 / q6_ui $end
$var wire 1 0 q5_ui $end
$var wire 1 1 q4_ui $end
$var wire 1 2 q3_ui $end
$var wire 1 3 q2_ui $end
$var wire 1 4 q1_ui $end
$var wire 5 5 out [4:0] $end
$var wire 2 6 mode_out [1:0] $end
$var reg 1 7 rst_ui $end
$var reg 1 8 sel $end
$var reg 1 9 t $end
$var reg 10 : x [9:0] $end
$scope module dmx $end
$var wire 1 ; Press_in $end
$var wire 1 8 select $end
$var reg 2 < Mode_out [1:0] $end
$upscope $end
$scope module enc $end
$var wire 10 = D_in [9:0] $end
$var reg 5 > BCD_out [4:0] $end
$upscope $end
$scope module input_array $end
$var wire 1 7 clear $end
$var wire 4 ? reg_in1 [3:0] $end
$var wire 4 @ reg_in2 [3:0] $end
$var wire 4 A reg_in3 [3:0] $end
$var wire 4 B reg_in4 [3:0] $end
$var wire 4 C reg_in5 [3:0] $end
$var wire 4 D reg_in6 [3:0] $end
$var wire 2 E reg_mode [1:0] $end
$var wire 4 F reg_out6 [3:0] $end
$var wire 4 G reg_out5 [3:0] $end
$var wire 4 H reg_out4 [3:0] $end
$var wire 4 I reg_out3 [3:0] $end
$var wire 4 J reg_out2 [3:0] $end
$var wire 4 K reg_out1 [3:0] $end
$var wire 1 ( clk6 $end
$var wire 1 * clk5 $end
$var wire 1 . clk4 $end
$var wire 1 0 clk3 $end
$var wire 1 / clk2 $end
$var wire 1 1 clk1 $end
$scope module reg1 $end
$var wire 4 L reg_in [3:0] $end
$var wire 2 M reg_mode [1:0] $end
$var wire 1 7 reset $end
$var wire 1 1 clock $end
$var reg 4 N reg_out [3:0] $end
$upscope $end
$scope module reg2 $end
$var wire 4 O reg_in [3:0] $end
$var wire 2 P reg_mode [1:0] $end
$var wire 1 7 reset $end
$var wire 1 / clock $end
$var reg 4 Q reg_out [3:0] $end
$upscope $end
$scope module reg3 $end
$var wire 4 R reg_in [3:0] $end
$var wire 2 S reg_mode [1:0] $end
$var wire 1 7 reset $end
$var wire 1 0 clock $end
$var reg 4 T reg_out [3:0] $end
$upscope $end
$scope module reg4 $end
$var wire 4 U reg_in [3:0] $end
$var wire 2 V reg_mode [1:0] $end
$var wire 1 7 reset $end
$var wire 1 . clock $end
$var reg 4 W reg_out [3:0] $end
$upscope $end
$scope module reg5 $end
$var wire 4 X reg_in [3:0] $end
$var wire 2 Y reg_mode [1:0] $end
$var wire 1 7 reset $end
$var wire 1 * clock $end
$var reg 4 Z reg_out [3:0] $end
$upscope $end
$scope module reg6 $end
$var wire 4 [ reg_in [3:0] $end
$var wire 2 \ reg_mode [1:0] $end
$var wire 1 7 reset $end
$var wire 1 ( clock $end
$var reg 4 ] reg_out [3:0] $end
$upscope $end
$upscope $end
$scope module input_t_ff $end
$var wire 1 ^ clk $end
$var wire 1 4 q1 $end
$var wire 1 3 q2 $end
$var wire 1 2 q3 $end
$var wire 1 - qbar1 $end
$var wire 1 , qbar2 $end
$var wire 1 + qbar3 $end
$var wire 1 7 rst $end
$var wire 1 9 t $end
$var wire 1 _ t3_qbar $end
$var wire 1 ` t3_q $end
$var wire 1 a t2_qbar $end
$var wire 1 b t2_q $end
$var wire 1 c t1_qbar $end
$var wire 1 d t1_q $end
$var wire 1 ' qbar7 $end
$var wire 1 ( qbar6 $end
$var wire 1 ) qbar5 $end
$var wire 1 * qbar4 $end
$var wire 1 . q7 $end
$var wire 1 / q6 $end
$var wire 1 0 q5 $end
$var wire 1 1 q4 $end
$scope module t1 $end
$var wire 1 ^ clk $end
$var wire 1 c qbar $end
$var wire 1 7 rst $end
$var wire 1 9 t $end
$var reg 1 d q $end
$upscope $end
$scope module t2 $end
$var wire 1 d clk $end
$var wire 1 a qbar $end
$var wire 1 7 rst $end
$var wire 1 9 t $end
$var reg 1 b q $end
$upscope $end
$scope module t3 $end
$var wire 1 c clk $end
$var wire 1 _ qbar $end
$var wire 1 7 rst $end
$var wire 1 9 t $end
$var reg 1 ` q $end
$upscope $end
$scope module t4 $end
$var wire 1 b clk $end
$var wire 1 * qbar $end
$var wire 1 7 rst $end
$var wire 1 9 t $end
$var reg 1 1 q $end
$upscope $end
$scope module t5 $end
$var wire 1 a clk $end
$var wire 1 ) qbar $end
$var wire 1 7 rst $end
$var wire 1 9 t $end
$var reg 1 0 q $end
$upscope $end
$scope module t6 $end
$var wire 1 ` clk $end
$var wire 1 ( qbar $end
$var wire 1 7 rst $end
$var wire 1 9 t $end
$var reg 1 / q $end
$upscope $end
$scope module t7 $end
$var wire 1 _ clk $end
$var wire 1 ' qbar $end
$var wire 1 7 rst $end
$var wire 1 9 t $end
$var reg 1 . q $end
$upscope $end
$upscope $end
$upscope $end
$enddefinitions $end
$comment Show the parameter values. $end
$dumpall
$end
#0
$dumpvars
0d
1c
0b
1a
0`
1_
0^
b0 ]
b11 \
b0 [
b0 Z
b11 Y
b0 X
b0 W
b11 V
b0 U
b0 T
b11 S
b0 R
b0 Q
b11 P
b0 O
b0 N
b11 M
b0 L
b0 K
b0 J
b0 I
b0 H
b0 G
b0 F
b11 E
b0 D
b0 C
b0 B
b0 A
b0 @
b0 ?
b0 >
b0 =
b0 <
0;
b0 :
09
08
17
b0 6
b0 5
04
03
02
01
00
0/
0.
1-
1,
1+
1*
1)
1(
1'
b0 &
b0 %
b0 $
b0 #
b0 "
b0 !
$end
#1
19
#2
07
#7
b10 &
b10 K
b10 N
0*
11
0,
0a
13
1b
0-
0c
14
1d
1^
b1 6
b1 <
b10 D
b10 [
b10 C
b10 X
b10 B
b10 U
b10 A
b10 R
b10 @
b10 O
b10 ?
b10 L
1;
b10010 5
b10010 >
b100 :
b100 =
#12
0^
b0 6
b0 <
b0 D
b0 [
b0 C
b0 X
b0 B
b0 U
b0 A
b0 R
b0 @
b0 O
b0 ?
b0 L
0;
b0 5
b0 >
b0 :
b0 =
#17
b1 %
b1 J
b1 Q
0(
1/
0+
0_
12
1`
1-
1c
04
0d
1^
b1 6
b1 <
b1 D
b1 [
b1 C
b1 X
b1 B
b1 U
b1 A
b1 R
b1 @
b1 O
b1 ?
b1 L
1;
b10001 5
b10001 >
b10 :
b10 =
#22
0^
b0 6
b0 <
b0 D
b0 [
b0 C
b0 X
b0 B
b0 U
b0 A
b0 R
b0 @
b0 O
b0 ?
b0 L
0;
b0 5
b0 >
b0 :
b0 =
#27
b1001 $
b1001 I
b1001 T
0)
10
1,
1a
03
0b
0-
0c
14
1d
1^
b1 6
b1 <
b1001 D
b1001 [
b1001 C
b1001 X
b1001 B
b1001 U
b1001 A
b1001 R
b1001 @
b1001 O
b1001 ?
b1001 L
1;
b11001 5
b11001 >
b1000000000 :
b1000000000 =
#32
0^
b0 6
b0 <
b0 D
b0 [
b0 C
b0 X
b0 B
b0 U
b0 A
b0 R
b0 @
b0 O
b0 ?
b0 L
0;
b0 5
b0 >
b0 :
b0 =
#37
b11 #
b11 H
b11 W
0'
1.
1+
1_
02
0`
1-
1c
04
0d
1^
b1 6
b1 <
b11 D
b11 [
b11 C
b11 X
b11 B
b11 U
b11 A
b11 R
b11 @
b11 O
b11 ?
b11 L
1;
b10011 5
b10011 >
b1000 :
b1000 =
#42
0^
b0 6
b0 <
b0 D
b0 [
b0 C
b0 X
b0 B
b0 U
b0 A
b0 R
b0 @
b0 O
b0 ?
b0 L
0;
b0 5
b0 >
b0 :
b0 =
#47
b101 "
b101 G
b101 Z
1*
01
0,
0a
13
1b
0-
0c
14
1d
1^
b1 6
b1 <
b101 D
b101 [
b101 C
b101 X
b101 B
b101 U
b101 A
b101 R
b101 @
b101 O
b101 ?
b101 L
1;
b10101 5
b10101 >
b100000 :
b100000 =
#52
0^
b0 6
b0 <
b0 D
b0 [
b0 C
b0 X
b0 B
b0 U
b0 A
b0 R
b0 @
b0 O
b0 ?
b0 L
0;
b0 5
b0 >
b0 :
b0 =
#57
b100 !
b100 F
b100 ]
1(
0/
0+
0_
12
1`
1-
1c
04
0d
1^
b1 6
b1 <
b100 D
b100 [
b100 C
b100 X
b100 B
b100 U
b100 A
b100 R
b100 @
b100 O
b100 ?
b100 L
1;
b10100 5
b10100 >
b10000 :
b10000 =
#62
0^
b0 6
b0 <
b0 D
b0 [
b0 C
b0 X
b0 B
b0 U
b0 A
b0 R
b0 @
b0 O
b0 ?
b0 L
0;
b0 5
b0 >
b0 :
b0 =
