desc_lib.v
// Design of encoder for inputs ~ makes use of Behavioural Description
module input_encoder (input [9:0] D_in, output reg [4:0] BCD_out);

    always @(D_in) begin
        casez (D_in)
            10'b0000000001: BCD_out = 5'b10000;  // D_in[0]
            10'b000000001?: BCD_out = 5'b10001;  // D_in[1]
            10'b00000001??: BCD_out = 5'b10010;  // D_in[2]
            10'b0000001???: BCD_out = 5'b10011;  // D_in[3]
            10'b000001????: BCD_out = 5'b10100;  // D_in[4]
            10'b00001?????: BCD_out = 5'b10101;  // D_in[5]
            10'b0001??????: BCD_out = 5'b10110;  // D_in[6]
            10'b001???????: BCD_out = 5'b10111;  // D_in[7]
            10'b01????????: BCD_out = 5'b11000;  // D_in[8]
            10'b1?????????: BCD_out = 5'b11001;  // D_in[9]
            default: BCD_out = 5'b00000;  // Default case to handle no-input states
        endcase

    end

endmodule

// Design of 1-2 Demultiplexer for clocking T flip-flops - makes use of Behavioural Description
module demux1_2 (output reg [1:0] Mode_out, input Press_in, input select);

    always @(Press_in, select) begin
        Mode_out = 2'b00;
        case (select)
            1'b0: Mode_out[0] = Press_in;
            1'b1: Mode_out[1] = Press_in;
            default: Mode_out = 2'b00;
        endcase
    end

endmodule

// Design of a T flipflops for clocking the memory for inputs sequentially - makes use of Behavioural Description
module t_ff (output reg q, output qbar, input clk, rst, t);

	assign qbar = ~q;

	always @(posedge clk)
	begin
		if (rst)
			q <= 0;
		else
			case(t)
				1'b0: q <= q;
				1'b1: q <= ~q;
			endcase
	end

    always @(negedge clk)
    begin
        if (rst)
			q <= 0;
    end
endmodule

// Design of a T-FF circuit for 4-bit storage clocking ~ makes use of Gate-Level and Dataflow Modeling
module t_ff_circuit (output wire q1, q2, q3, qbar1, qbar2, qbar3, input clk, rst, t);

    wire t1_q, t1_qbar;
    t_ff t1 (t1_q, t1_qbar, clk, rst, t);
    t_ff t2 (q2, qbar2, t1_q, rst, t);
    t_ff t3 (q3, qbar3, t1_qbar, rst, t);
    
    assign q1 = t1_q;
    assign qbar1 = t1_qbar;

endmodule

// Design of a T-FF circuit for 8-bit storage clocking ~ makes use of Gate-Level and Dataflow Modeling
module t_ff_circuit_upscaled (output wire q1, q2, q3, q4, q5, q6, q7,
    qbar1, qbar2, qbar3, qbar4, qbar5, qbar6, qbar7, input clk, rst, t);

    wire t1_q, t1_qbar, t2_q, t2_qbar, t3_q, t3_qbar;

    t_ff t1 (t1_q, t1_qbar, clk, rst, t);
    t_ff t2 (t2_q, t2_qbar, t1_q, rst, t);
    t_ff t3 (t3_q, t3_qbar, t1_qbar, rst, t);
    t_ff t4 (q4, qbar4, t2_q, rst, t);
    t_ff t5 (q5, qbar5, t2_qbar, rst, t);
    t_ff t6 (q6, qbar6, t3_q, rst, t);
    t_ff t7 (q7, qbar7, t3_qbar, rst, t);

    assign q1 = t1_q;
    assign qbar1 = t1_qbar;
    assign q2 = t2_q;
    assign qbar2 = t2_qbar;
    assign q3 = t3_q;
    assign qbar3 = t3_qbar;

endmodule

// Design of a universal shift register for BCD memory storage ~ makes use of Behavioural Modeling
module univ_shift_reg (output reg [3:0] reg_out, input clock, reset, input [1:0] reg_mode, input [3:0] reg_in);

    always @(reset) begin
        case (reset)
            1'b1: reg_out = 4'b0000;
            default: reg_out = reg_out;
        endcase
    end

    always @(posedge clock)
    begin
        if(reset)
        reg_out <= 4'b0000;
        else
        begin
            case(reg_mode)
            2'b00 : reg_out <= reg_out;      // locked mode, do nothing
            2'b01 : reg_out <= {reg_in[0], reg_out[3:1]};//reg_out >> 1; // RFSR
            2'b10 : reg_out <= {reg_out[2:0], reg_in[0]};//reg_out << 1; // LFSR
            2'b11 : reg_out <= reg_in;       // parallel in parallel out
            endcase
        end
    end
  
endmodule

// Design of a univeral shift register array for 4-digit BCD storage ~ makes use of Gate-level Modeling
module shift_reg_array (input clk1, clk2, clk3, clk4, clear,
    input [3:0] reg_in1, input [3:0] reg_in2, input [3:0] reg_in3, input [3:0] reg_in4, input [1:0] reg_mode, 
    output [3:0] reg_out1, output [3:0] reg_out2, output [3:0] reg_out3, output [3:0] reg_out4);

    univ_shift_reg reg1(reg_out1, clk1, clear, reg_mode, reg_in1);
    univ_shift_reg reg2(reg_out2, clk2, clear, reg_mode, reg_in2);
    univ_shift_reg reg3(reg_out3, clk3, clear, reg_mode, reg_in3);
    univ_shift_reg reg4(reg_out4, clk4, clear, reg_mode, reg_in4);

endmodule

// Design of a univeral shift register array for 8-digit BCD storage ~ makes use of Gate-level Modeling
module shift_reg_array_upscaled (input clk1, clk2, clk3, clk4, clk5, clk6, clk7, clk8, clear,
    input [3:0] reg_in1, input [3:0] reg_in2, input [3:0] reg_in3, input [3:0] reg_in4, input [3:0] reg_in5, input [3:0] reg_in6, input [3:0] reg_in7, input [3:0] reg_in8, input [1:0] reg_mode, 
    output [3:0] reg_out1, output [3:0] reg_out2, output [3:0] reg_out3, output [3:0] reg_out4, output [3:0] reg_out5, output [3:0] reg_out6, output [3:0] reg_out7, output [3:0] reg_out8);

    univ_shift_reg reg1(reg_out1, clk1, clear, reg_mode, reg_in1);
    univ_shift_reg reg2(reg_out2, clk2, clear, reg_mode, reg_in2);
    univ_shift_reg reg3(reg_out3, clk3, clear, reg_mode, reg_in3);
    univ_shift_reg reg4(reg_out4, clk4, clear, reg_mode, reg_in4);
    univ_shift_reg reg5(reg_out5, clk5, clear, reg_mode, reg_in5);
    univ_shift_reg reg6(reg_out6, clk6, clear, reg_mode, reg_in6);
    univ_shift_reg reg7(reg_out7, clk7, clear, reg_mode, reg_in7);
    univ_shift_reg reg8(reg_out8, clk8, clear, reg_mode, reg_in8);

endmodule

// Design of a 32-bit to 32-bit comparator for comparing secured password and user-inputted password ~ makes use of Dataflow Modeling
module eq_32_bit_comparator (input [31:0] in_1, in_2, output eq);

    assign eq = (in_1==in_2);

endmodule

// Design of a attempt counter in BCD ~ makes use of Behavioural Modeling
module attempt_bcd_counter (input reset, clk, output reg [3:0] count);

    always @(posedge clk) begin

        if (reset)
            count <= 4'b0000;
        else
            count <= count + 4'b0001;

    end

endmodule

module d_ff (output reg q, output qbar, input clk, rst, d);

	assign qbar = ~q;

	always @(posedge clk)
	begin
		if (rst)
			q <= 0;
		else
			q <= d;
	end

endmodule

module output_circuit (output alarm, unlocked, qbar, input is_equal, reset_alarm, bit_0, bit_2);

    wire w1, w2;

    d_ff d1(alarm, qbar, w2, reset_alarm, w2);
    not NOT1(w1, is_equal);
    and AND1(w2, bit_0, bit_2, w1), AND2(unlocked, qbar, is_equal);

endmodule

main_tb_upscaled.v
`timescale 1 ns / 1 ns
`include "desc_lib.v"

module main_tb;

    wire [4:0] out;
    wire [1:0] mode_out;
    wire [3:0] reg_out1, reg_out2, reg_out3, reg_out4, reg_out5, reg_out6, reg_out7, reg_out8;
    reg [9:0] x;
    reg sel, rst_ui, t;
    wire q1_ui, q2_ui, q3_ui, q4_ui, q5_ui, q6_ui, q7_ui, qbar1_ui, qbar2_ui, qbar3_ui, qbar4_ui, qbar5_ui, qbar6_ui, qbar7_ui;

    input_encoder enc(x, out);
    demux1_2 dmx(mode_out, out[4], sel);
    t_ff_circuit_upscaled input_t_ff(q1_ui, q2_ui, q3_ui, q4_ui, q5_ui, q6_ui, q7_ui, qbar1_ui, qbar2_ui, qbar3_ui, qbar4_ui, qbar5_ui, qbar6_ui, qbar7_ui, mode_out[0], rst_ui, t);
    shift_reg_array_upscaled input_array(q4_ui, q6_ui, q5_ui, q7_ui, qbar4_ui, qbar6_ui, qbar5_ui, qbar7_ui, rst_ui, out[3:0], out[3:0], out[3:0], out[3:0], out[3:0], out[3:0], out[3:0], out[3:0], 2'b11,
        reg_out1, reg_out2, reg_out3, reg_out4, reg_out5, reg_out6, reg_out7, reg_out8);

    /*
    initial begin
        clk = 0;
        forever #5 clk = ~clk;
    end
    */

    initial begin
        $dumpfile("main_tb.vcd"); $dumpvars(0, main_tb);

        $display("*** SIMULATING INPUT ENCODER ***");
        $display("\t BCD Output\t   Keypad Input\t    Demux Output\t\t\t\t     TFF Output\t\t\t\t\t\t\t\t\t\t       Shift Register Output");
        $monitor("\t   %b\t    %b\t         %b\t\t     clk1=%b, clk2=%b, clk3=%b, clk4=%b, clk5=%b, clk6=%b, clk7=%b, clk8=%b\t\t       SR1=%b, SR2=%b, SR3=%b, SR4=%b, SR5=%b, SR6=%b, SR7=%b, SR8=%b", out, x, mode_out, q4_ui, q6_ui, q5_ui, q7_ui, qbar4_ui, qbar6_ui, qbar5_ui, qbar7_ui, reg_out1, reg_out2, reg_out3, reg_out4, reg_out5, reg_out6, reg_out7, reg_out8);

        x[0]=0; x[1]=0; x[2]=0; x[3]=0; x[4]=0; 
        x[5]=0; x[6]=0; x[7]=0; x[8]=0; x[9]=0;

        sel = 0;
        t = 0;
        rst_ui = 1;
        
        
        #1 t = 1;
        #1 rst_ui = 0;
        #5 x[2]=1;
        #5 x[2]=0;
        #5 x[1]=1;
        #5 x[1]=0;
        #5 x[9]=1;
        #5 x[9]=0;
        #5 x[3]=1;
        #5 x[3]=0;
        #5 x[5]=1;
        #5 x[5]=0;
        #5 x[4]=1;
        #5 x[4]=0;
        #5 x[8]=1;
        #5 x[8]=0;
        #5 x[8]=1;
        #5 x[8]=0;
        #5 x[1]=1;
        #5 x[1]=0;
        #20 $finish;

    end


endmodule

main_tb.vcd
$date
	Tue Jul 16 18:53:56 2024
$end
$version
	Icarus Verilog
$end
$timescale
	1ns
$end
$scope module main_tb $end
$var wire 4 ! reg_out8 [3:0] $end
$var wire 4 " reg_out7 [3:0] $end
$var wire 4 # reg_out6 [3:0] $end
$var wire 4 $ reg_out5 [3:0] $end
$var wire 4 % reg_out4 [3:0] $end
$var wire 4 & reg_out3 [3:0] $end
$var wire 4 ' reg_out2 [3:0] $end
$var wire 4 ( reg_out1 [3:0] $end
$var wire 1 ) qbar7_ui $end
$var wire 1 * qbar6_ui $end
$var wire 1 + qbar5_ui $end
$var wire 1 , qbar4_ui $end
$var wire 1 - qbar3_ui $end
$var wire 1 . qbar2_ui $end
$var wire 1 / qbar1_ui $end
$var wire 1 0 q7_ui $end
$var wire 1 1 q6_ui $end
$var wire 1 2 q5_ui $end
$var wire 1 3 q4_ui $end
$var wire 1 4 q3_ui $end
$var wire 1 5 q2_ui $end
$var wire 1 6 q1_ui $end
$var wire 5 7 out [4:0] $end
$var wire 2 8 mode_out [1:0] $end
$var reg 1 9 rst_ui $end
$var reg 1 : sel $end
$var reg 1 ; t $end
$var reg 10 < x [9:0] $end
$scope module dmx $end
$var wire 1 = Press_in $end
$var wire 1 : select $end
$var reg 2 > Mode_out [1:0] $end
$upscope $end
$scope module enc $end
$var wire 10 ? D_in [9:0] $end
$var reg 5 @ BCD_out [4:0] $end
$upscope $end
$scope module input_array $end
$var wire 1 9 clear $end
$var wire 4 A reg_in1 [3:0] $end
$var wire 4 B reg_in2 [3:0] $end
$var wire 4 C reg_in3 [3:0] $end
$var wire 4 D reg_in4 [3:0] $end
$var wire 4 E reg_in5 [3:0] $end
$var wire 4 F reg_in6 [3:0] $end
$var wire 4 G reg_in7 [3:0] $end
$var wire 4 H reg_in8 [3:0] $end
$var wire 2 I reg_mode [1:0] $end
$var wire 4 J reg_out8 [3:0] $end
$var wire 4 K reg_out7 [3:0] $end
$var wire 4 L reg_out6 [3:0] $end
$var wire 4 M reg_out5 [3:0] $end
$var wire 4 N reg_out4 [3:0] $end
$var wire 4 O reg_out3 [3:0] $end
$var wire 4 P reg_out2 [3:0] $end
$var wire 4 Q reg_out1 [3:0] $end
$var wire 1 ) clk8 $end
$var wire 1 + clk7 $end
$var wire 1 * clk6 $end
$var wire 1 , clk5 $end
$var wire 1 0 clk4 $end
$var wire 1 2 clk3 $end
$var wire 1 1 clk2 $end
$var wire 1 3 clk1 $end
$scope module reg1 $end
$var wire 4 R reg_in [3:0] $end
$var wire 2 S reg_mode [1:0] $end
$var wire 1 9 reset $end
$var wire 1 3 clock $end
$var reg 4 T reg_out [3:0] $end
$upscope $end
$scope module reg2 $end
$var wire 4 U reg_in [3:0] $end
$var wire 2 V reg_mode [1:0] $end
$var wire 1 9 reset $end
$var wire 1 1 clock $end
$var reg 4 W reg_out [3:0] $end
$upscope $end
$scope module reg3 $end
$var wire 4 X reg_in [3:0] $end
$var wire 2 Y reg_mode [1:0] $end
$var wire 1 9 reset $end
$var wire 1 2 clock $end
$var reg 4 Z reg_out [3:0] $end
$upscope $end
$scope module reg4 $end
$var wire 4 [ reg_in [3:0] $end
$var wire 2 \ reg_mode [1:0] $end
$var wire 1 9 reset $end
$var wire 1 0 clock $end
$var reg 4 ] reg_out [3:0] $end
$upscope $end
$scope module reg5 $end
$var wire 4 ^ reg_in [3:0] $end
$var wire 2 _ reg_mode [1:0] $end
$var wire 1 9 reset $end
$var wire 1 , clock $end
$var reg 4 ` reg_out [3:0] $end
$upscope $end
$scope module reg6 $end
$var wire 4 a reg_in [3:0] $end
$var wire 2 b reg_mode [1:0] $end
$var wire 1 9 reset $end
$var wire 1 * clock $end
$var reg 4 c reg_out [3:0] $end
$upscope $end
$scope module reg7 $end
$var wire 4 d reg_in [3:0] $end
$var wire 2 e reg_mode [1:0] $end
$var wire 1 9 reset $end
$var wire 1 + clock $end
$var reg 4 f reg_out [3:0] $end
$upscope $end
$scope module reg8 $end
$var wire 4 g reg_in [3:0] $end
$var wire 2 h reg_mode [1:0] $end
$var wire 1 9 reset $end
$var wire 1 ) clock $end
$var reg 4 i reg_out [3:0] $end
$upscope $end
$upscope $end
$scope module input_t_ff $end
$var wire 1 j clk $end
$var wire 1 6 q1 $end
$var wire 1 5 q2 $end
$var wire 1 4 q3 $end
$var wire 1 / qbar1 $end
$var wire 1 . qbar2 $end
$var wire 1 - qbar3 $end
$var wire 1 9 rst $end
$var wire 1 ; t $end
$var wire 1 k t3_qbar $end
$var wire 1 l t3_q $end
$var wire 1 m t2_qbar $end
$var wire 1 n t2_q $end
$var wire 1 o t1_qbar $end
$var wire 1 p t1_q $end
$var wire 1 ) qbar7 $end
$var wire 1 * qbar6 $end
$var wire 1 + qbar5 $end
$var wire 1 , qbar4 $end
$var wire 1 0 q7 $end
$var wire 1 1 q6 $end
$var wire 1 2 q5 $end
$var wire 1 3 q4 $end
$scope module t1 $end
$var wire 1 j clk $end
$var wire 1 o qbar $end
$var wire 1 9 rst $end
$var wire 1 ; t $end
$var reg 1 p q $end
$upscope $end
$scope module t2 $end
$var wire 1 p clk $end
$var wire 1 m qbar $end
$var wire 1 9 rst $end
$var wire 1 ; t $end
$var reg 1 n q $end
$upscope $end
$scope module t3 $end
$var wire 1 o clk $end
$var wire 1 k qbar $end
$var wire 1 9 rst $end
$var wire 1 ; t $end
$var reg 1 l q $end
$upscope $end
$scope module t4 $end
$var wire 1 n clk $end
$var wire 1 , qbar $end
$var wire 1 9 rst $end
$var wire 1 ; t $end
$var reg 1 3 q $end
$upscope $end
$scope module t5 $end
$var wire 1 m clk $end
$var wire 1 + qbar $end
$var wire 1 9 rst $end
$var wire 1 ; t $end
$var reg 1 2 q $end
$upscope $end
$scope module t6 $end
$var wire 1 l clk $end
$var wire 1 * qbar $end
$var wire 1 9 rst $end
$var wire 1 ; t $end
$var reg 1 1 q $end
$upscope $end
$scope module t7 $end
$var wire 1 k clk $end
$var wire 1 ) qbar $end
$var wire 1 9 rst $end
$var wire 1 ; t $end
$var reg 1 0 q $end
$upscope $end
$upscope $end
$upscope $end
$enddefinitions $end
$comment Show the parameter values. $end
$dumpall
$end
#0
$dumpvars
0p
1o
0n
1m
0l
1k
0j
b0 i
b11 h
b0 g
b0 f
b11 e
b0 d
b0 c
b11 b
b0 a
b0 `
b11 _
b0 ^
b0 ]
b11 \
b0 [
b0 Z
b11 Y
b0 X
b0 W
b11 V
b0 U
b0 T
b11 S
b0 R
b0 Q
b0 P
b0 O
b0 N
b0 M
b0 L
b0 K
b0 J
b11 I
b0 H
b0 G
b0 F
b0 E
b0 D
b0 C
b0 B
b0 A
b0 @
b0 ?
b0 >
0=
b0 <
0;
0:
19
b0 8
b0 7
06
05
04
03
02
01
00
1/
1.
1-
1,
1+
1*
1)
b0 (
b0 '
b0 &
b0 %
b0 $
b0 #
b0 "
b0 !
$end
#1
1;
#2
09
#7
b10 (
b10 Q
b10 T
0,
13
0.
0m
15
1n
0/
0o
16
1p
1j
b1 8
b1 >
b10 H
b10 g
b10 G
b10 d
b10 F
b10 a
b10 E
b10 ^
b10 D
b10 [
b10 C
b10 X
b10 B
b10 U
b10 A
b10 R
1=
b10010 7
b10010 @
b100 <
b100 ?
#12
0j
b0 8
b0 >
b0 H
b0 g
b0 G
b0 d
b0 F
b0 a
b0 E
b0 ^
b0 D
b0 [
b0 C
b0 X
b0 B
b0 U
b0 A
b0 R
0=
b0 7
b0 @
b0 <
b0 ?
#17
b1 '
b1 P
b1 W
0*
11
0-
0k
14
1l
1/
1o
06
0p
1j
b1 8
b1 >
b1 H
b1 g
b1 G
b1 d
b1 F
b1 a
b1 E
b1 ^
b1 D
b1 [
b1 C
b1 X
b1 B
b1 U
b1 A
b1 R
1=
b10001 7
b10001 @
b10 <
b10 ?
#22
0j
b0 8
b0 >
b0 H
b0 g
b0 G
b0 d
b0 F
b0 a
b0 E
b0 ^
b0 D
b0 [
b0 C
b0 X
b0 B
b0 U
b0 A
b0 R
0=
b0 7
b0 @
b0 <
b0 ?
#27
b1001 &
b1001 O
b1001 Z
0+
12
1.
1m
05
0n
0/
0o
16
1p
1j
b1 8
b1 >
b1001 H
b1001 g
b1001 G
b1001 d
b1001 F
b1001 a
b1001 E
b1001 ^
b1001 D
b1001 [
b1001 C
b1001 X
b1001 B
b1001 U
b1001 A
b1001 R
1=
b11001 7
b11001 @
b1000000000 <
b1000000000 ?
#32
0j
b0 8
b0 >
b0 H
b0 g
b0 G
b0 d
b0 F
b0 a
b0 E
b0 ^
b0 D
b0 [
b0 C
b0 X
b0 B
b0 U
b0 A
b0 R
0=
b0 7
b0 @
b0 <
b0 ?
#37
b11 %
b11 N
b11 ]
0)
10
1-
1k
04
0l
1/
1o
06
0p
1j
b1 8
b1 >
b11 H
b11 g
b11 G
b11 d
b11 F
b11 a
b11 E
b11 ^
b11 D
b11 [
b11 C
b11 X
b11 B
b11 U
b11 A
b11 R
1=
b10011 7
b10011 @
b1000 <
b1000 ?
#42
0j
b0 8
b0 >
b0 H
b0 g
b0 G
b0 d
b0 F
b0 a
b0 E
b0 ^
b0 D
b0 [
b0 C
b0 X
b0 B
b0 U
b0 A
b0 R
0=
b0 7
b0 @
b0 <
b0 ?
#47
b101 $
b101 M
b101 `
1,
03
0.
0m
15
1n
0/
0o
16
1p
1j
b1 8
b1 >
b101 H
b101 g
b101 G
b101 d
b101 F
b101 a
b101 E
b101 ^
b101 D
b101 [
b101 C
b101 X
b101 B
b101 U
b101 A
b101 R
1=
b10101 7
b10101 @
b100000 <
b100000 ?
#52
0j
b0 8
b0 >
b0 H
b0 g
b0 G
b0 d
b0 F
b0 a
b0 E
b0 ^
b0 D
b0 [
b0 C
b0 X
b0 B
b0 U
b0 A
b0 R
0=
b0 7
b0 @
b0 <
b0 ?
#57
b100 #
b100 L
b100 c
1*
01
0-
0k
14
1l
1/
1o
06
0p
1j
b1 8
b1 >
b100 H
b100 g
b100 G
b100 d
b100 F
b100 a
b100 E
b100 ^
b100 D
b100 [
b100 C
b100 X
b100 B
b100 U
b100 A
b100 R
1=
b10100 7
b10100 @
b10000 <
b10000 ?
#62
0j
b0 8
b0 >
b0 H
b0 g
b0 G
b0 d
b0 F
b0 a
b0 E
b0 ^
b0 D
b0 [
b0 C
b0 X
b0 B
b0 U
b0 A
b0 R
0=
b0 7
b0 @
b0 <
b0 ?
#67
b1000 "
b1000 K
b1000 f
1+
02
1.
1m
05
0n
0/
0o
16
1p
1j
b1 8
b1 >
b1000 H
b1000 g
b1000 G
b1000 d
b1000 F
b1000 a
b1000 E
b1000 ^
b1000 D
b1000 [
b1000 C
b1000 X
b1000 B
b1000 U
b1000 A
b1000 R
1=
b11000 7
b11000 @
b100000000 <
b100000000 ?
#72
0j
b0 8
b0 >
b0 H
b0 g
b0 G
b0 d
b0 F
b0 a
b0 E
b0 ^
b0 D
b0 [
b0 C
b0 X
b0 B
b0 U
b0 A
b0 R
0=
b0 7
b0 @
b0 <
b0 ?
#77
b1000 !
b1000 J
b1000 i
1)
00
1-
1k
04
0l
1/
1o
06
0p
1j
b1 8
b1 >
b1000 H
b1000 g
b1000 G
b1000 d
b1000 F
b1000 a
b1000 E
b1000 ^
b1000 D
b1000 [
b1000 C
b1000 X
b1000 B
b1000 U
b1000 A
b1000 R
1=
b11000 7
b11000 @
b100000000 <
b100000000 ?
#82
0j
b0 8
b0 >
b0 H
b0 g
b0 G
b0 d
b0 F
b0 a
b0 E
b0 ^
b0 D
b0 [
b0 C
b0 X
b0 B
b0 U
b0 A
b0 R
0=
b0 7
b0 @
b0 <
b0 ?
#87
b1 (
b1 Q
b1 T
0,
13
0.
0m
15
1n
0/
0o
16
1p
1j
b1 8
b1 >
b1 H
b1 g
b1 G
b1 d
b1 F
b1 a
b1 E
b1 ^
b1 D
b1 [
b1 C
b1 X
b1 B
b1 U
b1 A
b1 R
1=
b10001 7
b10001 @
b10 <
b10 ?
#92
0j
b0 8
b0 >
b0 H
b0 g
b0 G
b0 d
b0 F
b0 a
b0 E
b0 ^
b0 D
b0 [
b0 C
b0 X
b0 B
b0 U
b0 A
b0 R
0=
b0 7
b0 @
b0 <
b0 ?
