desc_lib.v
// Design of encoder for inputs ~ makes use of Behavioural Description
module input_encoder (input [9:0] D_in, output reg [4:0] BCD_out);

    always @(D_in) begin
        casez (D_in)
            10'b0000000001: BCD_out = 5'b10000;  // D_in[0]
            10'b000000001?: BCD_out = 5'b10001;  // D_in[1]
            10'b00000001??: BCD_out = 5'b10010;  // D_in[2]
            10'b0000001???: BCD_out = 5'b10011;  // D_in[3]
            10'b000001????: BCD_out = 5'b10100;  // D_in[4]
            10'b00001?????: BCD_out = 5'b10101;  // D_in[5]
            10'b0001??????: BCD_out = 5'b10110;  // D_in[6]
            10'b001???????: BCD_out = 5'b10111;  // D_in[7]
            10'b01????????: BCD_out = 5'b11000;  // D_in[8]
            10'b1?????????: BCD_out = 5'b11001;  // D_in[9]
            default: BCD_out = 5'b00000;  // Default case to handle no-input states
        endcase

    end

endmodule

// Design of 1-2 Demultiplexer for clocking T flip-flops - makes use of Behavioural Description
module demux1_2 (output reg [1:0] Mode_out, input Press_in, input select);

    always @(Press_in, select) begin
        Mode_out = 2'b00;
        case (select)
            1'b0: Mode_out[0] = Press_in;
            1'b1: Mode_out[1] = Press_in;
            default: Mode_out = 2'b00;
        endcase
    end

endmodule

// Design of a T flipflops for clocking the memory for inputs sequentially - makes use of Behavioural Description
module t_ff (output reg q, output qbar, input clk, rst, t);

	assign qbar = ~q;

	always @(posedge clk)
	begin
		if (rst)
			q <= 0;
		else
			case(t)
				1'b0: q <= q;
				1'b1: q <= ~q;
			endcase
	end

    always @(negedge clk)
    begin
        if (rst)
			q <= 0;
    end
endmodule

// Design of a T-FF circuit ~ makes use of Gate-Level Modelling
module t_ff_circuit (output wire q1, q2, q3, qbar1, qbar2, qbar3, input clk, rst, t);

    wire t1_q, t1_qbar;
    
    t_ff t1 (t1_q, t1_qbar, clk, rst, t);
    
    t_ff t2 (q2, qbar2, t1_q, rst, t);

    t_ff t3 (q3, qbar3, t1_qbar, rst, t);
    
    assign q1 = t1_q;
    assign qbar1 = t1_qbar;

endmodule

module t_ff_circuit_upscaled (output wire q1, q2, q3, q4, q5, q6, q7,
    qbar1, qbar2, qbar3, qbar4, qbar5, qbar6, qbar7, input clk, rst, t);

    wire t1_q, t1_qbar, t2_q, t2_qbar, t3_q, t3_qbar;

    t_ff t1 (t1_q, t1_qbar, clk, rst, t);

    t_ff t2 (t2_q, t2_qbar, t1_q, rst, t);

    t_ff t3 (t3_q, t3_qbar, t1_qbar, rst, t);
    
    t_ff t4 (q4, qbar4, t2_q, rst, t);

    t_ff t5 (q5, qbar5, t2_qbar, rst, t);

    t_ff t6 (q6, qbar6, t3_q, rst, t);

    t_ff t7 (q7, qbar7, t3_qbar, rst, t);

    assign q1 = t1_q;
    assign qbar1 = t1_qbar;
    assign q2 = t2_q;
    assign qbar2 = t2_qbar;
    assign q3 = t3_q;
    assign qbar3 = t3_qbar;
    
endmodule

module univ_shift_reg (output reg [3:0] reg_out, input clock, reset, input [1:0] reg_mode, input [3:0] reg_in);

    always @(reset) begin
        case (reset)
            1'b1: reg_out = 4'b0000;
            default: reg_out = reg_out;
        endcase
    end

    always @(posedge clock)
    begin
        if(reset)
        reg_out <= 4'b0000;
        else
        begin
            case(reg_mode)
            2'b00 : reg_out <= reg_out;      // locked mode, do nothing
            2'b01 : reg_out <= {reg_in[0], reg_out[3:1]};//reg_out >> 1; // RFSR
            2'b10 : reg_out <= {reg_out[2:0], reg_in[0]};//reg_out << 1; // LFSR
            2'b11 : reg_out <= reg_in;       // parallel in parallel out
            endcase
        end
    end
  
endmodule

module shift_reg_array (input clk1, clk2, clk3, clk4, clear,
    input [3:0] reg_in1, input [3:0] reg_in2, input [3:0] reg_in3, input [3:0] reg_in4, input [1:0] reg_mode, 
    output [3:0] reg_out1, output [3:0] reg_out2, output [3:0] reg_out3, output [3:0] reg_out4);

    univ_shift_reg reg1(reg_out1, clk1, clear, reg_mode, reg_in1);
    univ_shift_reg reg2(reg_out2, clk2, clear, reg_mode, reg_in2);
    univ_shift_reg reg3(reg_out3, clk3, clear, reg_mode, reg_in3);
    univ_shift_reg reg4(reg_out4, clk4, clear, reg_mode, reg_in4);

endmodule

module shift_reg_array_upscaled (input clk1, clk2, clk3, clk4, clk5, clk6, clk7, clk8, clear,
    input [3:0] reg_in1, input [3:0] reg_in2, input [3:0] reg_in3, input [3:0] reg_in4, input [3:0] reg_in5, input [3:0] reg_in6, input [3:0] reg_in7, input [3:0] reg_in8, input [1:0] reg_mode, 
    output [3:0] reg_out1, output [3:0] reg_out2, output [3:0] reg_out3, output [3:0] reg_out4, output [3:0] reg_out5, output [3:0] reg_out6, output [3:0] reg_out7, output [3:0] reg_out8);

    univ_shift_reg reg1(reg_out1, clk1, clear, reg_mode, reg_in1);
    univ_shift_reg reg2(reg_out2, clk2, clear, reg_mode, reg_in2);
    univ_shift_reg reg3(reg_out3, clk3, clear, reg_mode, reg_in3);
    univ_shift_reg reg4(reg_out4, clk4, clear, reg_mode, reg_in4);
    univ_shift_reg reg5(reg_out5, clk5, clear, reg_mode, reg_in5);
    univ_shift_reg reg6(reg_out6, clk6, clear, reg_mode, reg_in6);
    univ_shift_reg reg7(reg_out7, clk7, clear, reg_mode, reg_in7);
    univ_shift_reg reg8(reg_out8, clk8, clear, reg_mode, reg_in8);

endmodule

module eq_32_bit_comparator (input [31:0] in_1, in_2, output eq);

    assign eq = (in_1==in_2);

endmodule

module attempt_bcd_counter (input reset, clk, output reg [3:0] count);

    always @(posedge clk) begin

        if (reset)
            count <= 4'b0000;
        else
            count <= count + 4'b0001;

    end

endmodule

main_tb_upscaled.v
`timescale 1 ns / 1 ns
`include "desc_lib.v"

module main_tb;

    wire [4:0] out;
    wire [1:0] mode_out;
    wire [3:0] reg_out1, reg_out2, reg_out3, reg_out4, reg_out5, reg_out6, reg_out7, reg_out8;
    wire [3:0] sp_reg_out1, sp_reg_out2, sp_reg_out3, sp_reg_out4, sp_reg_out5, sp_reg_out6, sp_reg_out7, sp_reg_out8, attempt_count;
    reg [9:0] x;
    reg sel, rst_ui, rst_sp, rst_attempts, t;
    wire q1_ui, q2_ui, q3_ui, q4_ui, q5_ui, q6_ui, q7_ui, qbar1_ui, qbar2_ui, qbar3_ui, qbar4_ui, qbar5_ui, qbar6_ui, qbar7_ui;
    wire q1_sp, q2_sp, q3_sp, q4_sp, q5_sp, q6_sp, q7_sp, qbar1_sp, qbar2_sp, qbar3_sp, qbar4_sp, qbar5_sp, qbar6_sp, qbar7_sp;
    wire comp_out;

    input_encoder enc(x, out);
    demux1_2 dmx(mode_out, out[4], sel);

    t_ff_circuit_upscaled input_t_ff(q1_ui, q2_ui, q3_ui, q4_ui, q5_ui, q6_ui, q7_ui, qbar1_ui, qbar2_ui, qbar3_ui, qbar4_ui, qbar5_ui, qbar6_ui, qbar7_ui, mode_out[0], rst_ui, t);
    shift_reg_array_upscaled input_array(q4_ui, q6_ui, q5_ui, q7_ui, qbar4_ui, qbar6_ui, qbar5_ui, qbar7_ui, rst_ui, out[3:0], out[3:0], out[3:0], out[3:0], out[3:0], out[3:0], out[3:0], out[3:0], 2'b11,
        reg_out1, reg_out2, reg_out3, reg_out4, reg_out5, reg_out6, reg_out7, reg_out8);

    t_ff_circuit_upscaled input_t_ff_2(q1_sp, q2_sp, q3_sp, q4_sp, q5_sp, q6_sp, q7_sp, qbar1_sp, qbar2_sp, qbar3_sp, qbar4_sp, qbar5_sp, qbar6_sp, qbar7_sp, mode_out[1], rst_sp, t);
    shift_reg_array_upscaled input_array_2(q4_sp, q6_sp, q5_sp, q7_sp, qbar4_sp, qbar6_sp, qbar5_sp, qbar7_sp, rst_sp, out[3:0], out[3:0], out[3:0], out[3:0], out[3:0], out[3:0], out[3:0], out[3:0], 2'b11,
        sp_reg_out1, sp_reg_out2, sp_reg_out3, sp_reg_out4, sp_reg_out5, sp_reg_out6, sp_reg_out7, sp_reg_out8);

    eq_32_bit_comparator comp_circ({reg_out1, reg_out2, reg_out3, reg_out4, reg_out5, reg_out6, reg_out7, reg_out8}, {sp_reg_out1, sp_reg_out2, sp_reg_out3, sp_reg_out4, sp_reg_out5, sp_reg_out6, sp_reg_out7, sp_reg_out8}, comp_out);
    
    attempt_bcd_counter attempts(rst_attempts, qbar7_ui, attempt_count);
    /*
    initial begin
        clk = 0;
        forever #5 clk = ~clk;
    end
    */

    initial begin
        $dumpfile("main_tb.vcd"); $dumpvars(0, main_tb);

        $display("*** SIMULATING INPUT ENCODER ***");
        $display("\t BCD Output\t   Keypad Input\t    Demux Output\t\t\t\t     TFF Output\t\t\t\t\t\t\t\t\t        (UI) Shift Register Output\t\t\t\t\t\t\t\t        (SP) Shift Register Output\t\t\t\t  Comparator Output\t\t Attempt");
        $monitor("\t   %b\t    %b\t         %b\t\t     clk1=%b, clk2=%b, clk3=%b, clk4=%b, clk5=%b, clk6=%b, clk7=%b, clk8=%b\t\t       SR1=%b, SR2=%b, SR3=%b, SR4=%b, SR5=%b, SR6=%b, SR7=%b, SR8=%b\t\t       SR1=%b, SR2=%b, SR3=%b, SR4=%b, SR5=%b, SR6=%b, SR7=%b, SR8=%b\t\t   %b\t\t    %b", out, x, mode_out, q4_ui, q6_ui, q5_ui, q7_ui, qbar4_ui, qbar6_ui, qbar5_ui, qbar7_ui, reg_out1, reg_out2, reg_out3, reg_out4, reg_out5, reg_out6, reg_out7, reg_out8, sp_reg_out1, sp_reg_out2, sp_reg_out3, sp_reg_out4, sp_reg_out5, sp_reg_out6, sp_reg_out7, sp_reg_out8, comp_out, attempt_count);

        x[0]=0; x[1]=0; x[2]=0; x[3]=0; x[4]=0; 
        x[5]=0; x[6]=0; x[7]=0; x[8]=0; x[9]=0;

        sel = 0;
        t = 0;
        rst_ui = 1;
        rst_attempts = 1;
        rst_sp = 1;
        
        fork
            #1 t = 1;
            #1 rst_ui = 0;
            #1 rst_sp = 0;
            #1 rst_attempts = 0;
        join   

        #5 x[2]=1;
        #5 x[2]=0;
        #5 x[1]=1;
        #5 x[1]=0;
        #5 x[9]=1;
        #5 x[9]=0;
        #5 x[3]=1;
        #5 x[3]=0;
        #5 x[5]=1;
        #5 x[5]=0;
        #5 x[4]=1;
        #5 x[4]=0;
        #5 x[8]=1;
        #5 x[8]=0;
        #5 x[8]=1;
        #5 x[8]=0;

        #5 x[2]=1;
        #5 x[2]=0;
        #5 x[1]=1;
        #5 x[1]=0;
        #5 x[9]=1;
        #5 x[9]=0;
        #5 x[3]=1;
        #5 x[3]=0;
        #5 x[5]=1;
        #5 x[5]=0;
        #5 x[4]=1;
        #5 x[4]=0;
        #5 x[7]=1;
        #5 x[7]=0;
        #5 x[7]=1;
        #5 x[7]=0;

        #20 $finish;

    end


endmodule

main_tb.vcd
$date
	Wed Jul 17 14:18:11 2024
$end
$version
	Icarus Verilog
$end
$timescale
	1ns
$end
$scope module main_tb $end
$var wire 4 ! sp_reg_out8 [3:0] $end
$var wire 4 " sp_reg_out7 [3:0] $end
$var wire 4 # sp_reg_out6 [3:0] $end
$var wire 4 $ sp_reg_out5 [3:0] $end
$var wire 4 % sp_reg_out4 [3:0] $end
$var wire 4 & sp_reg_out3 [3:0] $end
$var wire 4 ' sp_reg_out2 [3:0] $end
$var wire 4 ( sp_reg_out1 [3:0] $end
$var wire 4 ) reg_out8 [3:0] $end
$var wire 4 * reg_out7 [3:0] $end
$var wire 4 + reg_out6 [3:0] $end
$var wire 4 , reg_out5 [3:0] $end
$var wire 4 - reg_out4 [3:0] $end
$var wire 4 . reg_out3 [3:0] $end
$var wire 4 / reg_out2 [3:0] $end
$var wire 4 0 reg_out1 [3:0] $end
$var wire 1 1 qbar7_ui $end
$var wire 1 2 qbar7_sp $end
$var wire 1 3 qbar6_ui $end
$var wire 1 4 qbar6_sp $end
$var wire 1 5 qbar5_ui $end
$var wire 1 6 qbar5_sp $end
$var wire 1 7 qbar4_ui $end
$var wire 1 8 qbar4_sp $end
$var wire 1 9 qbar3_ui $end
$var wire 1 : qbar3_sp $end
$var wire 1 ; qbar2_ui $end
$var wire 1 < qbar2_sp $end
$var wire 1 = qbar1_ui $end
$var wire 1 > qbar1_sp $end
$var wire 1 ? q7_ui $end
$var wire 1 @ q7_sp $end
$var wire 1 A q6_ui $end
$var wire 1 B q6_sp $end
$var wire 1 C q5_ui $end
$var wire 1 D q5_sp $end
$var wire 1 E q4_ui $end
$var wire 1 F q4_sp $end
$var wire 1 G q3_ui $end
$var wire 1 H q3_sp $end
$var wire 1 I q2_ui $end
$var wire 1 J q2_sp $end
$var wire 1 K q1_ui $end
$var wire 1 L q1_sp $end
$var wire 5 M out [4:0] $end
$var wire 2 N mode_out [1:0] $end
$var wire 1 O comp_out $end
$var wire 4 P attempt_count [3:0] $end
$var reg 1 Q rst_attempts $end
$var reg 1 R rst_sp $end
$var reg 1 S rst_ui $end
$var reg 1 T sel $end
$var reg 1 U t $end
$var reg 10 V x [9:0] $end
$scope module attempts $end
$var wire 1 Q reset $end
$var wire 1 1 clk $end
$var reg 4 W count [3:0] $end
$upscope $end
$scope module comp_circ $end
$var wire 32 X in_1 [31:0] $end
$var wire 32 Y in_2 [31:0] $end
$var wire 1 O eq $end
$upscope $end
$scope module dmx $end
$var wire 1 Z Press_in $end
$var wire 1 T select $end
$var reg 2 [ Mode_out [1:0] $end
$upscope $end
$scope module enc $end
$var wire 10 \ D_in [9:0] $end
$var reg 5 ] BCD_out [4:0] $end
$upscope $end
$scope module input_array $end
$var wire 1 S clear $end
$var wire 4 ^ reg_in1 [3:0] $end
$var wire 4 _ reg_in2 [3:0] $end
$var wire 4 ` reg_in3 [3:0] $end
$var wire 4 a reg_in4 [3:0] $end
$var wire 4 b reg_in5 [3:0] $end
$var wire 4 c reg_in6 [3:0] $end
$var wire 4 d reg_in7 [3:0] $end
$var wire 4 e reg_in8 [3:0] $end
$var wire 2 f reg_mode [1:0] $end
$var wire 4 g reg_out8 [3:0] $end
$var wire 4 h reg_out7 [3:0] $end
$var wire 4 i reg_out6 [3:0] $end
$var wire 4 j reg_out5 [3:0] $end
$var wire 4 k reg_out4 [3:0] $end
$var wire 4 l reg_out3 [3:0] $end
$var wire 4 m reg_out2 [3:0] $end
$var wire 4 n reg_out1 [3:0] $end
$var wire 1 1 clk8 $end
$var wire 1 5 clk7 $end
$var wire 1 3 clk6 $end
$var wire 1 7 clk5 $end
$var wire 1 ? clk4 $end
$var wire 1 C clk3 $end
$var wire 1 A clk2 $end
$var wire 1 E clk1 $end
$scope module reg1 $end
$var wire 4 o reg_in [3:0] $end
$var wire 2 p reg_mode [1:0] $end
$var wire 1 S reset $end
$var wire 1 E clock $end
$var reg 4 q reg_out [3:0] $end
$upscope $end
$scope module reg2 $end
$var wire 4 r reg_in [3:0] $end
$var wire 2 s reg_mode [1:0] $end
$var wire 1 S reset $end
$var wire 1 A clock $end
$var reg 4 t reg_out [3:0] $end
$upscope $end
$scope module reg3 $end
$var wire 4 u reg_in [3:0] $end
$var wire 2 v reg_mode [1:0] $end
$var wire 1 S reset $end
$var wire 1 C clock $end
$var reg 4 w reg_out [3:0] $end
$upscope $end
$scope module reg4 $end
$var wire 4 x reg_in [3:0] $end
$var wire 2 y reg_mode [1:0] $end
$var wire 1 S reset $end
$var wire 1 ? clock $end
$var reg 4 z reg_out [3:0] $end
$upscope $end
$scope module reg5 $end
$var wire 4 { reg_in [3:0] $end
$var wire 2 | reg_mode [1:0] $end
$var wire 1 S reset $end
$var wire 1 7 clock $end
$var reg 4 } reg_out [3:0] $end
$upscope $end
$scope module reg6 $end
$var wire 4 ~ reg_in [3:0] $end
$var wire 2 !" reg_mode [1:0] $end
$var wire 1 S reset $end
$var wire 1 3 clock $end
$var reg 4 "" reg_out [3:0] $end
$upscope $end
$scope module reg7 $end
$var wire 4 #" reg_in [3:0] $end
$var wire 2 $" reg_mode [1:0] $end
$var wire 1 S reset $end
$var wire 1 5 clock $end
$var reg 4 %" reg_out [3:0] $end
$upscope $end
$scope module reg8 $end
$var wire 4 &" reg_in [3:0] $end
$var wire 2 '" reg_mode [1:0] $end
$var wire 1 S reset $end
$var wire 1 1 clock $end
$var reg 4 (" reg_out [3:0] $end
$upscope $end
$upscope $end
$scope module input_array_2 $end
$var wire 1 R clear $end
$var wire 4 )" reg_in1 [3:0] $end
$var wire 4 *" reg_in2 [3:0] $end
$var wire 4 +" reg_in3 [3:0] $end
$var wire 4 ," reg_in4 [3:0] $end
$var wire 4 -" reg_in5 [3:0] $end
$var wire 4 ." reg_in6 [3:0] $end
$var wire 4 /" reg_in7 [3:0] $end
$var wire 4 0" reg_in8 [3:0] $end
$var wire 2 1" reg_mode [1:0] $end
$var wire 4 2" reg_out8 [3:0] $end
$var wire 4 3" reg_out7 [3:0] $end
$var wire 4 4" reg_out6 [3:0] $end
$var wire 4 5" reg_out5 [3:0] $end
$var wire 4 6" reg_out4 [3:0] $end
$var wire 4 7" reg_out3 [3:0] $end
$var wire 4 8" reg_out2 [3:0] $end
$var wire 4 9" reg_out1 [3:0] $end
$var wire 1 2 clk8 $end
$var wire 1 6 clk7 $end
$var wire 1 4 clk6 $end
$var wire 1 8 clk5 $end
$var wire 1 @ clk4 $end
$var wire 1 D clk3 $end
$var wire 1 B clk2 $end
$var wire 1 F clk1 $end
$scope module reg1 $end
$var wire 4 :" reg_in [3:0] $end
$var wire 2 ;" reg_mode [1:0] $end
$var wire 1 R reset $end
$var wire 1 F clock $end
$var reg 4 <" reg_out [3:0] $end
$upscope $end
$scope module reg2 $end
$var wire 4 =" reg_in [3:0] $end
$var wire 2 >" reg_mode [1:0] $end
$var wire 1 R reset $end
$var wire 1 B clock $end
$var reg 4 ?" reg_out [3:0] $end
$upscope $end
$scope module reg3 $end
$var wire 4 @" reg_in [3:0] $end
$var wire 2 A" reg_mode [1:0] $end
$var wire 1 R reset $end
$var wire 1 D clock $end
$var reg 4 B" reg_out [3:0] $end
$upscope $end
$scope module reg4 $end
$var wire 4 C" reg_in [3:0] $end
$var wire 2 D" reg_mode [1:0] $end
$var wire 1 R reset $end
$var wire 1 @ clock $end
$var reg 4 E" reg_out [3:0] $end
$upscope $end
$scope module reg5 $end
$var wire 4 F" reg_in [3:0] $end
$var wire 2 G" reg_mode [1:0] $end
$var wire 1 R reset $end
$var wire 1 8 clock $end
$var reg 4 H" reg_out [3:0] $end
$upscope $end
$scope module reg6 $end
$var wire 4 I" reg_in [3:0] $end
$var wire 2 J" reg_mode [1:0] $end
$var wire 1 R reset $end
$var wire 1 4 clock $end
$var reg 4 K" reg_out [3:0] $end
$upscope $end
$scope module reg7 $end
$var wire 4 L" reg_in [3:0] $end
$var wire 2 M" reg_mode [1:0] $end
$var wire 1 R reset $end
$var wire 1 6 clock $end
$var reg 4 N" reg_out [3:0] $end
$upscope $end
$scope module reg8 $end
$var wire 4 O" reg_in [3:0] $end
$var wire 2 P" reg_mode [1:0] $end
$var wire 1 R reset $end
$var wire 1 2 clock $end
$var reg 4 Q" reg_out [3:0] $end
$upscope $end
$upscope $end
$scope module input_t_ff $end
$var wire 1 R" clk $end
$var wire 1 K q1 $end
$var wire 1 I q2 $end
$var wire 1 G q3 $end
$var wire 1 = qbar1 $end
$var wire 1 ; qbar2 $end
$var wire 1 9 qbar3 $end
$var wire 1 S rst $end
$var wire 1 U t $end
$var wire 1 S" t3_qbar $end
$var wire 1 T" t3_q $end
$var wire 1 U" t2_qbar $end
$var wire 1 V" t2_q $end
$var wire 1 W" t1_qbar $end
$var wire 1 X" t1_q $end
$var wire 1 1 qbar7 $end
$var wire 1 3 qbar6 $end
$var wire 1 5 qbar5 $end
$var wire 1 7 qbar4 $end
$var wire 1 ? q7 $end
$var wire 1 A q6 $end
$var wire 1 C q5 $end
$var wire 1 E q4 $end
$scope module t1 $end
$var wire 1 R" clk $end
$var wire 1 W" qbar $end
$var wire 1 S rst $end
$var wire 1 U t $end
$var reg 1 X" q $end
$upscope $end
$scope module t2 $end
$var wire 1 X" clk $end
$var wire 1 U" qbar $end
$var wire 1 S rst $end
$var wire 1 U t $end
$var reg 1 V" q $end
$upscope $end
$scope module t3 $end
$var wire 1 W" clk $end
$var wire 1 S" qbar $end
$var wire 1 S rst $end
$var wire 1 U t $end
$var reg 1 T" q $end
$upscope $end
$scope module t4 $end
$var wire 1 V" clk $end
$var wire 1 7 qbar $end
$var wire 1 S rst $end
$var wire 1 U t $end
$var reg 1 E q $end
$upscope $end
$scope module t5 $end
$var wire 1 U" clk $end
$var wire 1 5 qbar $end
$var wire 1 S rst $end
$var wire 1 U t $end
$var reg 1 C q $end
$upscope $end
$scope module t6 $end
$var wire 1 T" clk $end
$var wire 1 3 qbar $end
$var wire 1 S rst $end
$var wire 1 U t $end
$var reg 1 A q $end
$upscope $end
$scope module t7 $end
$var wire 1 S" clk $end
$var wire 1 1 qbar $end
$var wire 1 S rst $end
$var wire 1 U t $end
$var reg 1 ? q $end
$upscope $end
$upscope $end
$scope module input_t_ff_2 $end
$var wire 1 Y" clk $end
$var wire 1 L q1 $end
$var wire 1 J q2 $end
$var wire 1 H q3 $end
$var wire 1 > qbar1 $end
$var wire 1 < qbar2 $end
$var wire 1 : qbar3 $end
$var wire 1 R rst $end
$var wire 1 U t $end
$var wire 1 Z" t3_qbar $end
$var wire 1 [" t3_q $end
$var wire 1 \" t2_qbar $end
$var wire 1 ]" t2_q $end
$var wire 1 ^" t1_qbar $end
$var wire 1 _" t1_q $end
$var wire 1 2 qbar7 $end
$var wire 1 4 qbar6 $end
$var wire 1 6 qbar5 $end
$var wire 1 8 qbar4 $end
$var wire 1 @ q7 $end
$var wire 1 B q6 $end
$var wire 1 D q5 $end
$var wire 1 F q4 $end
$scope module t1 $end
$var wire 1 Y" clk $end
$var wire 1 ^" qbar $end
$var wire 1 R rst $end
$var wire 1 U t $end
$var reg 1 _" q $end
$upscope $end
$scope module t2 $end
$var wire 1 _" clk $end
$var wire 1 \" qbar $end
$var wire 1 R rst $end
$var wire 1 U t $end
$var reg 1 ]" q $end
$upscope $end
$scope module t3 $end
$var wire 1 ^" clk $end
$var wire 1 Z" qbar $end
$var wire 1 R rst $end
$var wire 1 U t $end
$var reg 1 [" q $end
$upscope $end
$scope module t4 $end
$var wire 1 ]" clk $end
$var wire 1 8 qbar $end
$var wire 1 R rst $end
$var wire 1 U t $end
$var reg 1 F q $end
$upscope $end
$scope module t5 $end
$var wire 1 \" clk $end
$var wire 1 6 qbar $end
$var wire 1 R rst $end
$var wire 1 U t $end
$var reg 1 D q $end
$upscope $end
$scope module t6 $end
$var wire 1 [" clk $end
$var wire 1 4 qbar $end
$var wire 1 R rst $end
$var wire 1 U t $end
$var reg 1 B q $end
$upscope $end
$scope module t7 $end
$var wire 1 Z" clk $end
$var wire 1 2 qbar $end
$var wire 1 R rst $end
$var wire 1 U t $end
$var reg 1 @ q $end
$upscope $end
$upscope $end
$upscope $end
$enddefinitions $end
$comment Show the parameter values. $end
$dumpall
$end
#0
$dumpvars
0_"
1^"
0]"
1\"
0["
1Z"
0Y"
0X"
1W"
0V"
1U"
0T"
1S"
0R"
b0 Q"
b11 P"
b0 O"
b0 N"
b11 M"
b0 L"
b0 K"
b11 J"
b0 I"
b0 H"
b11 G"
b0 F"
b0 E"
b11 D"
b0 C"
b0 B"
b11 A"
b0 @"
b0 ?"
b11 >"
b0 ="
b0 <"
b11 ;"
b0 :"
b0 9"
b0 8"
b0 7"
b0 6"
b0 5"
b0 4"
b0 3"
b0 2"
b11 1"
b0 0"
b0 /"
b0 ."
b0 -"
b0 ,"
b0 +"
b0 *"
b0 )"
b0 ("
b11 '"
b0 &"
b0 %"
b11 $"
b0 #"
b0 ""
b11 !"
b0 ~
b0 }
b11 |
b0 {
b0 z
b11 y
b0 x
b0 w
b11 v
b0 u
b0 t
b11 s
b0 r
b0 q
b11 p
b0 o
b0 n
b0 m
b0 l
b0 k
b0 j
b0 i
b0 h
b0 g
b11 f
b0 e
b0 d
b0 c
b0 b
b0 a
b0 `
b0 _
b0 ^
b0 ]
b0 \
b0 [
0Z
b0 Y
b0 X
b0 W
b0 V
0U
0T
1S
1R
1Q
b0 P
1O
b0 N
b0 M
0L
0K
0J
0I
0H
0G
0F
0E
0D
0C
0B
0A
0@
0?
1>
1=
1<
1;
1:
19
18
17
16
15
14
13
12
11
b0 0
b0 /
b0 .
b0 -
b0 ,
b0 +
b0 *
b0 )
b0 (
b0 '
b0 &
b0 %
b0 $
b0 #
b0 "
b0 !
$end
#1
1U
0S
0R
0Q
#6
0O
b100000000000000000000000000000 X
b10 0
b10 n
b10 q
07
1E
0;
0U"
1I
1V"
0=
0W"
1K
1X"
1R"
b1 N
b1 [
b10 0"
b10 O"
b10 /"
b10 L"
b10 ."
b10 I"
b10 -"
b10 F"
b10 ,"
b10 C"
b10 +"
b10 @"
b10 *"
b10 ="
b10 )"
b10 :"
b10 e
b10 &"
b10 d
b10 #"
b10 c
b10 ~
b10 b
b10 {
b10 a
b10 x
b10 `
b10 u
b10 _
b10 r
b10 ^
b10 o
1Z
b10010 M
b10010 ]
b100 V
b100 \
#11
0R"
b0 N
b0 [
b0 0"
b0 O"
b0 /"
b0 L"
b0 ."
b0 I"
b0 -"
b0 F"
b0 ,"
b0 C"
b0 +"
b0 @"
b0 *"
b0 ="
b0 )"
b0 :"
b0 e
b0 &"
b0 d
b0 #"
b0 c
b0 ~
b0 b
b0 {
b0 a
b0 x
b0 `
b0 u
b0 _
b0 r
b0 ^
b0 o
0Z
b0 M
b0 ]
b0 V
b0 \
#16
b100001000000000000000000000000 X
b1 /
b1 m
b1 t
03
1A
09
0S"
1G
1T"
1=
1W"
0K
0X"
1R"
b1 N
b1 [
b1 0"
b1 O"
b1 /"
b1 L"
b1 ."
b1 I"
b1 -"
b1 F"
b1 ,"
b1 C"
b1 +"
b1 @"
b1 *"
b1 ="
b1 )"
b1 :"
b1 e
b1 &"
b1 d
b1 #"
b1 c
b1 ~
b1 b
b1 {
b1 a
b1 x
b1 `
b1 u
b1 _
b1 r
b1 ^
b1 o
1Z
b10001 M
b10001 ]
b10 V
b10 \
#21
0R"
b0 N
b0 [
b0 0"
b0 O"
b0 /"
b0 L"
b0 ."
b0 I"
b0 -"
b0 F"
b0 ,"
b0 C"
b0 +"
b0 @"
b0 *"
b0 ="
b0 )"
b0 :"
b0 e
b0 &"
b0 d
b0 #"
b0 c
b0 ~
b0 b
b0 {
b0 a
b0 x
b0 `
b0 u
b0 _
b0 r
b0 ^
b0 o
0Z
b0 M
b0 ]
b0 V
b0 \
#26
b100001100100000000000000000000 X
b1001 .
b1001 l
b1001 w
05
1C
1;
1U"
0I
0V"
0=
0W"
1K
1X"
1R"
b1 N
b1 [
b1001 0"
b1001 O"
b1001 /"
b1001 L"
b1001 ."
b1001 I"
b1001 -"
b1001 F"
b1001 ,"
b1001 C"
b1001 +"
b1001 @"
b1001 *"
b1001 ="
b1001 )"
b1001 :"
b1001 e
b1001 &"
b1001 d
b1001 #"
b1001 c
b1001 ~
b1001 b
b1001 {
b1001 a
b1001 x
b1001 `
b1001 u
b1001 _
b1001 r
b1001 ^
b1001 o
1Z
b11001 M
b11001 ]
b1000000000 V
b1000000000 \
#31
0R"
b0 N
b0 [
b0 0"
b0 O"
b0 /"
b0 L"
b0 ."
b0 I"
b0 -"
b0 F"
b0 ,"
b0 C"
b0 +"
b0 @"
b0 *"
b0 ="
b0 )"
b0 :"
b0 e
b0 &"
b0 d
b0 #"
b0 c
b0 ~
b0 b
b0 {
b0 a
b0 x
b0 `
b0 u
b0 _
b0 r
b0 ^
b0 o
0Z
b0 M
b0 ]
b0 V
b0 \
#36
b100001100100110000000000000000 X
b11 -
b11 k
b11 z
01
1?
19
1S"
0G
0T"
1=
1W"
0K
0X"
1R"
b1 N
b1 [
b11 0"
b11 O"
b11 /"
b11 L"
b11 ."
b11 I"
b11 -"
b11 F"
b11 ,"
b11 C"
b11 +"
b11 @"
b11 *"
b11 ="
b11 )"
b11 :"
b11 e
b11 &"
b11 d
b11 #"
b11 c
b11 ~
b11 b
b11 {
b11 a
b11 x
b11 `
b11 u
b11 _
b11 r
b11 ^
b11 o
1Z
b10011 M
b10011 ]
b1000 V
b1000 \
#41
0R"
b0 N
b0 [
b0 0"
b0 O"
b0 /"
b0 L"
b0 ."
b0 I"
b0 -"
b0 F"
b0 ,"
b0 C"
b0 +"
b0 @"
b0 *"
b0 ="
b0 )"
b0 :"
b0 e
b0 &"
b0 d
b0 #"
b0 c
b0 ~
b0 b
b0 {
b0 a
b0 x
b0 `
b0 u
b0 _
b0 r
b0 ^
b0 o
0Z
b0 M
b0 ]
b0 V
b0 \
#46
b100001100100110101000000000000 X
b101 ,
b101 j
b101 }
17
0E
0;
0U"
1I
1V"
0=
0W"
1K
1X"
1R"
b1 N
b1 [
b101 0"
b101 O"
b101 /"
b101 L"
b101 ."
b101 I"
b101 -"
b101 F"
b101 ,"
b101 C"
b101 +"
b101 @"
b101 *"
b101 ="
b101 )"
b101 :"
b101 e
b101 &"
b101 d
b101 #"
b101 c
b101 ~
b101 b
b101 {
b101 a
b101 x
b101 `
b101 u
b101 _
b101 r
b101 ^
b101 o
1Z
b10101 M
b10101 ]
b100000 V
b100000 \
#51
0R"
b0 N
b0 [
b0 0"
b0 O"
b0 /"
b0 L"
b0 ."
b0 I"
b0 -"
b0 F"
b0 ,"
b0 C"
b0 +"
b0 @"
b0 *"
b0 ="
b0 )"
b0 :"
b0 e
b0 &"
b0 d
b0 #"
b0 c
b0 ~
b0 b
b0 {
b0 a
b0 x
b0 `
b0 u
b0 _
b0 r
b0 ^
b0 o
0Z
b0 M
b0 ]
b0 V
b0 \
