desc_lib.v
// Design of encoder for inputs ~ makes use of Behavioural Description
module input_encoder (input [9:0] D_in, output reg [4:0] BCD_out);

    always @(D_in) begin
        casez (D_in)
            10'b0000000001: BCD_out = 5'b10000;  // D_in[0]
            10'b000000001?: BCD_out = 5'b10001;  // D_in[1]
            10'b00000001??: BCD_out = 5'b10010;  // D_in[2]
            10'b0000001???: BCD_out = 5'b10011;  // D_in[3]
            10'b000001????: BCD_out = 5'b10100;  // D_in[4]
            10'b00001?????: BCD_out = 5'b10101;  // D_in[5]
            10'b0001??????: BCD_out = 5'b10110;  // D_in[6]
            10'b001???????: BCD_out = 5'b10111;  // D_in[7]
            10'b01????????: BCD_out = 5'b11000;  // D_in[8]
            10'b1?????????: BCD_out = 5'b11001;  // D_in[9]
            default: BCD_out = 5'b00000;  // Default case to handle no-input states
        endcase

    end

endmodule

// Design of 1-2 Demultiplexer for clocking JK flip-flops - makes use of Behavioural Description
module demux1_2 (output reg [1:0] Mode_out, input Press_in, input select);

    always @(Press_in, select) begin
        Mode_out = 2'b00;
        case (select)
            1'b0: Mode_out[0] = Press_in;
            1'b1: Mode_out[1] = Press_in;
            default: Mode_out = 2'b00;
        endcase
    end

endmodule

// Design of a T flipflops for clocking the memory for inputs sequentially - makes use of Behavioural Description
module t_ff (output reg q, output qbar, input clk, rst, t);

	assign qbar = ~q;

	always @(clk)
	begin
		if (rst)
			q <= 0;
		else
			case(t)
				1'b0: q <= q;
				1'b1: q <= ~q;
			endcase
	end
endmodule

// Design of a T-FF circuit ~ makes use of Gate-Level Modelling
module t_ff_circuit (output wire q1, q2, q3, qbar1, qbar2, qbar3, input clk, rst, t);

    // Internal wires for clock connections
    wire t1_q, t1_qbar;
    
    // Instantiate the first T flip-flop
    t_ff t1 (t1_q, t1_qbar, clk, rst, t);
    
    // Instantiate the second T flip-flop, clocked by q of the first flip-flop
    t_ff t2 (q2, qbar2, t1_q, rst, t);
    
    // Instantiate the third T flip-flop, clocked by qbar of the first flip-flop
    t_ff t3 (q3, qbar3, t1_qbar, rst, t);
    
    // Output assignments
    assign q1 = t1_q;
    assign qbar1 = t1_qbar;

endmodule

main_tb.v
`timescale 1 ns / 1 ns
`include "desc_lib.v"

module main_tb;

    wire [4:0] out;
    wire [1:0] mode_out;
    reg [9:0] x;
    reg sel, reset, t;
    wire q1, q2, q3, qbar1, qbar2, qbar3;

    input_encoder enc(x, out);
    demux1_2 dmx(mode_out, out[4], sel);
    t_ff_circuit uut(q1, q2, q3, qbar1, qbar2, qbar3, mode_out[0], reset, t);

    /*
    initial begin
        clk = 0;
        forever #5 clk = ~clk;
    end
    */

    initial begin
        $dumpfile("main_tb.vcd"); $dumpvars(0, main_tb);

        $display("*** SIMULATING INPUT ENCODER ***");
        $display("\t BCD Output\t   Keypad Input\t    Demux Output\t\t     TFF Output");
        $monitor("\t   %b\t    %b\t         %b\t\t     clk1=%b, clk2=%b, clk3=%b, clk4=%b", out, x, mode_out, q2, qbar2, q3, qbar3);

        x[0]=0; x[1]=0; x[2]=0; x[3]=0; x[4]=0; 
        x[5]=0; x[6]=0; x[7]=0; x[8]=0; x[9]=0;

        sel = 0;
        t = 0;
        reset = 1;
        
        #1 t = 1;
        #1 reset = 0;
        #5 x[0]=1;
        #5 x[0]=0;
        #5 x[1]=1;
        #5 x[1]=0;
        #5 x[9]=1;
        #5 x[9]=0;
        #20 $finish;

    end


endmodule

main_tb.vcd
$date
	Mon Jul 15 16:13:51 2024
$end
$version
	Icarus Verilog
$end
$timescale
	1ns
$end
$scope module main_tb $end
$var wire 1 ! qbar3 $end
$var wire 1 " qbar2 $end
$var wire 1 # qbar1 $end
$var wire 1 $ q3 $end
$var wire 1 % q2 $end
$var wire 1 & q1 $end
$var wire 5 ' out [4:0] $end
$var wire 2 ( mode_out [1:0] $end
$var reg 1 ) reset $end
$var reg 1 * sel $end
$var reg 1 + t $end
$var reg 10 , x [9:0] $end
$scope module dmx $end
$var wire 1 - Press_in $end
$var wire 1 * select $end
$var reg 2 . Mode_out [1:0] $end
$upscope $end
$scope module enc $end
$var wire 10 / D_in [9:0] $end
$var reg 5 0 BCD_out [4:0] $end
$upscope $end
$scope module uut $end
$var wire 1 1 clk $end
$var wire 1 & q1 $end
$var wire 1 # qbar1 $end
$var wire 1 ) rst $end
$var wire 1 + t $end
$var wire 1 2 t1_qbar $end
$var wire 1 3 t1_q $end
$var wire 1 ! qbar3 $end
$var wire 1 " qbar2 $end
$var wire 1 $ q3 $end
$var wire 1 % q2 $end
$scope module t1 $end
$var wire 1 1 clk $end
$var wire 1 2 qbar $end
$var wire 1 ) rst $end
$var wire 1 + t $end
$var reg 1 3 q $end
$upscope $end
$scope module t2 $end
$var wire 1 3 clk $end
$var wire 1 " qbar $end
$var wire 1 ) rst $end
$var wire 1 + t $end
$var reg 1 % q $end
$upscope $end
$scope module t3 $end
$var wire 1 2 clk $end
$var wire 1 ! qbar $end
$var wire 1 ) rst $end
$var wire 1 + t $end
$var reg 1 $ q $end
$upscope $end
$upscope $end
$upscope $end
$enddefinitions $end
$comment Show the parameter values. $end
$dumpall
$end
#0
$dumpvars
03
12
01
b0 0
b0 /
b0 .
0-
b0 ,
0+
0*
1)
b0 (
b0 '
0&
0%
0$
1#
1"
1!
$end
#1
1+
#2
0)
#7
0!
0"
1$
1%
0#
02
1&
13
11
b1 (
b1 .
1-
b10000 '
b10000 0
b1 ,
b1 /
#12
1!
1"
0$
0%
1#
12
0&
03
01
b0 (
b0 .
0-
b0 '
b0 0
b0 ,
b0 /
#17
0!
0"
1$
1%
0#
02
1&
13
11
b1 (
b1 .
1-
b10001 '
b10001 0
b10 ,
b10 /
#22
1!
1"
0$
0%
1#
12
0&
03
01
b0 (
b0 .
0-
b0 '
b0 0
b0 ,
b0 /
#27
0!
0"
1$
1%
0#
02
1&
13
11
b1 (
b1 .
1-
b11001 '
b11001 0
b1000000000 ,
b1000000000 /
#32
1!
1"
0$
0%
1#
12
0&
03
01
b0 (
b0 .
0-
b0 '
b0 0
b0 ,
b0 /
