desc_lib.v
// Design of encoder for inputs ~ makes use of Behavioural Description
module input_encoder (input [9:0] D_in, output reg [4:0] BCD_out);

    always @(D_in) begin
        casez (D_in)
            10'b0000000001: BCD_out = 5'b10000;  // D_in[0]
            10'b000000001?: BCD_out = 5'b10001;  // D_in[1]
            10'b00000001??: BCD_out = 5'b10010;  // D_in[2]
            10'b0000001???: BCD_out = 5'b10011;  // D_in[3]
            10'b000001????: BCD_out = 5'b10100;  // D_in[4]
            10'b00001?????: BCD_out = 5'b10101;  // D_in[5]
            10'b0001??????: BCD_out = 5'b10110;  // D_in[6]
            10'b001???????: BCD_out = 5'b10111;  // D_in[7]
            10'b01????????: BCD_out = 5'b11000;  // D_in[8]
            10'b1?????????: BCD_out = 5'b11001;  // D_in[9]
            default: BCD_out = 5'b00000;  // Default case to handle no-input states
        endcase

    end

endmodule

// Design of 1-2 Demultiplexer for clocking T flip-flops - makes use of Behavioural Description
module demux1_2 (output reg [1:0] Mode_out, input Press_in, input select);

    always @(Press_in, select) begin
        Mode_out = 2'b00;
        case (select)
            1'b0: Mode_out[0] = Press_in;
            1'b1: Mode_out[1] = Press_in;
            default: Mode_out = 2'b00;
        endcase
    end

endmodule

// Design of a T flipflops for clocking the memory for inputs sequentially - makes use of Behavioural Description
module t_ff (output reg q, output qbar, input clk, rst, t);

	assign qbar = ~q;

	always @(posedge clk)
	begin
		if (rst)
			q <= 0;
		else
			case(t)
				1'b0: q <= q;
				1'b1: q <= ~q;
			endcase
	end

    always @(negedge clk)
    begin
        if (rst)
			q <= 0;
    end
endmodule

// Design of a T-FF circuit for 4-bit storage clocking ~ makes use of Gate-Level and Dataflow Modeling
module t_ff_circuit (output wire q1, q2, q3, qbar1, qbar2, qbar3, input clk, rst, t);

    wire t1_q, t1_qbar;
    t_ff t1 (t1_q, t1_qbar, clk, rst, t);
    t_ff t2 (q2, qbar2, t1_q, rst, t);
    t_ff t3 (q3, qbar3, t1_qbar, rst, t);
    
    assign q1 = t1_q;
    assign qbar1 = t1_qbar;

endmodule

// Design of a T-FF circuit for 8-bit storage clocking ~ makes use of Gate-Level and Dataflow Modeling
module t_ff_circuit_upscaled (output wire q1, q2, q3, q4, q5, q6, q7,
    qbar1, qbar2, qbar3, qbar4, qbar5, qbar6, qbar7, input clk, rst, t);

    wire t1_q, t1_qbar, t2_q, t2_qbar, t3_q, t3_qbar;

    t_ff t1 (t1_q, t1_qbar, clk, rst, t);
    t_ff t2 (t2_q, t2_qbar, t1_q, rst, t);
    t_ff t3 (t3_q, t3_qbar, t1_qbar, rst, t);
    t_ff t4 (q4, qbar4, t2_q, rst, t);
    t_ff t5 (q5, qbar5, t2_qbar, rst, t);
    t_ff t6 (q6, qbar6, t3_q, rst, t);
    t_ff t7 (q7, qbar7, t3_qbar, rst, t);

    assign q1 = t1_q;
    assign qbar1 = t1_qbar;
    assign q2 = t2_q;
    assign qbar2 = t2_qbar;
    assign q3 = t3_q;
    assign qbar3 = t3_qbar;

endmodule

// Design of a universal shift register for BCD memory storage ~ makes use of Behavioural Modeling
module univ_shift_reg (output reg [3:0] reg_out, input clock, reset, input [1:0] reg_mode, input [3:0] reg_in);

    always @(reset) begin
        case (reset)
            1'b1: reg_out = 4'b0000;
            default: reg_out = reg_out;
        endcase
    end

    always @(posedge clock)
    begin
        if(reset)
        reg_out <= 4'b0000;
        else
        begin
            case(reg_mode)
            2'b00 : reg_out <= reg_out;      // locked mode, do nothing
            2'b01 : reg_out <= {reg_in[0], reg_out[3:1]};//reg_out >> 1; // RFSR
            2'b10 : reg_out <= {reg_out[2:0], reg_in[0]};//reg_out << 1; // LFSR
            2'b11 : reg_out <= reg_in;       // parallel in parallel out
            endcase
        end
    end
  
endmodule

// Design of a univeral shift register array for 4-digit BCD storage ~ makes use of Gate-level Modeling
module shift_reg_array (input clk1, clk2, clk3, clk4, clear,
    input [3:0] reg_in1, input [3:0] reg_in2, input [3:0] reg_in3, input [3:0] reg_in4, input [1:0] reg_mode, 
    output [3:0] reg_out1, output [3:0] reg_out2, output [3:0] reg_out3, output [3:0] reg_out4);

    univ_shift_reg reg1(reg_out1, clk1, clear, reg_mode, reg_in1);
    univ_shift_reg reg2(reg_out2, clk2, clear, reg_mode, reg_in2);
    univ_shift_reg reg3(reg_out3, clk3, clear, reg_mode, reg_in3);
    univ_shift_reg reg4(reg_out4, clk4, clear, reg_mode, reg_in4);

endmodule

// Design of a univeral shift register array for 8-digit BCD storage ~ makes use of Gate-level Modeling
module shift_reg_array_upscaled (input clk1, clk2, clk3, clk4, clk5, clk6, clk7, clk8, clear,
    input [3:0] reg_in1, input [3:0] reg_in2, input [3:0] reg_in3, input [3:0] reg_in4, input [3:0] reg_in5, input [3:0] reg_in6, input [3:0] reg_in7, input [3:0] reg_in8, input [1:0] reg_mode, 
    output [3:0] reg_out1, output [3:0] reg_out2, output [3:0] reg_out3, output [3:0] reg_out4, output [3:0] reg_out5, output [3:0] reg_out6, output [3:0] reg_out7, output [3:0] reg_out8);

    univ_shift_reg reg1(reg_out1, clk1, clear, reg_mode, reg_in1);
    univ_shift_reg reg2(reg_out2, clk2, clear, reg_mode, reg_in2);
    univ_shift_reg reg3(reg_out3, clk3, clear, reg_mode, reg_in3);
    univ_shift_reg reg4(reg_out4, clk4, clear, reg_mode, reg_in4);
    univ_shift_reg reg5(reg_out5, clk5, clear, reg_mode, reg_in5);
    univ_shift_reg reg6(reg_out6, clk6, clear, reg_mode, reg_in6);
    univ_shift_reg reg7(reg_out7, clk7, clear, reg_mode, reg_in7);
    univ_shift_reg reg8(reg_out8, clk8, clear, reg_mode, reg_in8);

endmodule

// Design of a 32-bit to 32-bit comparator for comparing secured password and user-inputted password ~ makes use of Dataflow Modeling
module eq_32_bit_comparator (input [31:0] in_1, in_2, output eq);

    assign eq = (in_1==in_2);

endmodule

// Design of a attempt counter in BCD ~ makes use of Behavioural Modeling
module attempt_bcd_counter (input reset, clk, output reg [3:0] count);

    always @(posedge clk) begin

        if (reset)
            count <= 4'b0000;
        else
            count <= count + 4'b0001;

    end

endmodule

module d_ff (output reg q, output qbar, input clk, rst, d);

	assign qbar = ~q;

	always @(posedge clk)
	begin
		if (rst)
			q <= 0;
		else
			q <= d;
	end

endmodule

module output_circuit (output alarm, unlocked, qbar, input is_equal, reset_alarm, bit_0, bit_2);

    wire w1, w2;

    d_ff d1(alarm, qbar, w2, reset_alarm, w2);
    not NOT1(w1, is_equal);
    and AND1(w2, bit_0, bit_2, w1), AND2(unlocked, qbar, is_equal);

endmodule

main_tb_upscaled.v
`timescale 1 ns / 1 ns
`include "desc_lib.v"

module main_tb;

    wire [4:0] out;
    wire [1:0] mode_out;
    wire [3:0] reg_out1, reg_out2, reg_out3, reg_out4, reg_out5, reg_out6, reg_out7, reg_out8;
    wire [3:0] sp_reg_out1, sp_reg_out2, sp_reg_out3, sp_reg_out4, sp_reg_out5, sp_reg_out6, sp_reg_out7, sp_reg_out8, attempt_count;
    reg [9:0] x;
    reg sel, rst_ui, rst_sp, rst_attempts, rst_alarm, t;
    wire q1_ui, q2_ui, q3_ui, q4_ui, q5_ui, q6_ui, q7_ui, qbar1_ui, qbar2_ui, qbar3_ui, qbar4_ui, qbar5_ui, qbar6_ui, qbar7_ui;
    wire q1_sp, q2_sp, q3_sp, q4_sp, q5_sp, q6_sp, q7_sp, qbar1_sp, qbar2_sp, qbar3_sp, qbar4_sp, qbar5_sp, qbar6_sp, qbar7_sp;
    wire comp_out;
    wire alarm, unlocked, alarm_not_on; 

    input_encoder enc(x, out);
    demux1_2 dmx(mode_out, out[4], sel);

    t_ff_circuit_upscaled input_t_ff(q1_ui, q2_ui, q3_ui, q4_ui, q5_ui, q6_ui, q7_ui, qbar1_ui, qbar2_ui, qbar3_ui, qbar4_ui, qbar5_ui, qbar6_ui, qbar7_ui, mode_out[0], rst_ui, t);
    shift_reg_array_upscaled input_array(q4_ui, q6_ui, q5_ui, q7_ui, qbar4_ui, qbar6_ui, qbar5_ui, qbar7_ui, rst_ui, out[3:0], out[3:0], out[3:0], out[3:0], out[3:0], out[3:0], out[3:0], out[3:0], 2'b11,
        reg_out1, reg_out2, reg_out3, reg_out4, reg_out5, reg_out6, reg_out7, reg_out8);

    t_ff_circuit_upscaled input_t_ff_2(q1_sp, q2_sp, q3_sp, q4_sp, q5_sp, q6_sp, q7_sp, qbar1_sp, qbar2_sp, qbar3_sp, qbar4_sp, qbar5_sp, qbar6_sp, qbar7_sp, mode_out[1], rst_sp, t);
    shift_reg_array_upscaled input_array_2(q4_sp, q6_sp, q5_sp, q7_sp, qbar4_sp, qbar6_sp, qbar5_sp, qbar7_sp, rst_sp, out[3:0], out[3:0], out[3:0], out[3:0], out[3:0], out[3:0], out[3:0], out[3:0], 2'b11,
        sp_reg_out1, sp_reg_out2, sp_reg_out3, sp_reg_out4, sp_reg_out5, sp_reg_out6, sp_reg_out7, sp_reg_out8);

    eq_32_bit_comparator comp_circ({reg_out1, reg_out2, reg_out3, reg_out4, reg_out5, reg_out6, reg_out7, reg_out8}, {sp_reg_out1, sp_reg_out2, sp_reg_out3, sp_reg_out4, sp_reg_out5, sp_reg_out6, sp_reg_out7, sp_reg_out8}, comp_out);
    
    attempt_bcd_counter attempts(rst_attempts, qbar7_ui, attempt_count);

    output_circuit out_circ(alarm, unlocked, alarm_not_on, comp_out, rst_alarm, attempt_count[0], attempt_count[2]);
    /*
    initial begin
        clk = 0;
        forever #5 clk = ~clk;
    end
    */

    initial begin

        $dumpfile("main_tb.vcd"); $dumpvars(0, main_tb);

        $display("*** SIMULATING HDL DESIGN OF EXPERIMENT ***");
        $display("\t BCD Output\t   Keypad Input\t    Demux Output\t\t\t\t     TFF Output\t\t\t\t\t\t\t\t\t        (UI) Shift Register Output\t\t\t\t\t\t\t\t        (SP) Shift Register Output\t\t\t\t  Comparator Output\t   Attempt\t  Unlocked");
        $monitor("\t   %b\t    %b\t         %b\t\t     clk1=%b, clk2=%b, clk3=%b, clk4=%b, clk5=%b, clk6=%b, clk7=%b, clk8=%b\t\t       SR1=%b, SR2=%b, SR3=%b, SR4=%b, SR5=%b, SR6=%b, SR7=%b, SR8=%b\t\t       SR1=%b, SR2=%b, SR3=%b, SR4=%b, SR5=%b, SR6=%b, SR7=%b, SR8=%b\t\t   %b\t\t    %b\t     %b", out, x, mode_out, q4_ui, q6_ui, q5_ui, q7_ui, qbar4_ui, qbar6_ui, qbar5_ui, qbar7_ui, reg_out1, reg_out2, reg_out3, reg_out4, reg_out5, reg_out6, reg_out7, reg_out8, sp_reg_out1, sp_reg_out2, sp_reg_out3, sp_reg_out4, sp_reg_out5, sp_reg_out6, sp_reg_out7, sp_reg_out8, comp_out, attempt_count, unlocked);

        x[0]=0; x[1]=0; x[2]=0; x[3]=0; x[4]=0; 
        x[5]=0; x[6]=0; x[7]=0; x[8]=0; x[9]=0;

        sel = 0;
        t = 0;
        rst_ui = 1;
        rst_attempts = 1;
        rst_sp = 1;
        rst_alarm = 1;

    end

    initial fork
            #1 t = 1;
            #1 rst_ui = 0;
            #1 rst_sp = 0;
            #1 rst_attempts = 0;
            #1 rst_alarm = 0;
    join   

    initial begin


        #5 x[2]=1;
        #5 x[2]=0;
        #5 x[1]=1;
        #5 x[1]=0;
        #5 x[9]=1;
        #5 x[9]=0;
        #5 x[3]=1;
        #5 x[3]=0;
        #5 x[5]=1;
        #5 x[5]=0;
        #5 x[4]=1;
        #5 x[4]=0;
        #5 x[8]=1;
        #5 x[8]=0;
        #5 x[8]=1;
        #5 x[8]=0;

        #1 sel = 1;

        #5 x[2]=1;
        #5 x[2]=0;
        #5 x[1]=1;
        #5 x[1]=0;
        #5 x[9]=1;
        #5 x[9]=0;
        #5 x[3]=1;
        #5 x[3]=0;
        #5 x[5]=1;
        #5 x[5]=0;
        #5 x[4]=1;
        #5 x[4]=0;
        #5 x[8]=1;
        #5 x[8]=0;
        #5 x[8]=1;
        #5 x[8]=0;

        #20 $finish;

    end


endmodule

main_tb.vcd
$date
	Thu Jul 18 17:32:33 2024
$end
$version
	Icarus Verilog
$end
$timescale
	1ns
$end
$scope module main_tb $end
$var wire 1 ! unlocked $end
$var wire 4 " sp_reg_out8 [3:0] $end
$var wire 4 # sp_reg_out7 [3:0] $end
$var wire 4 $ sp_reg_out6 [3:0] $end
$var wire 4 % sp_reg_out5 [3:0] $end
$var wire 4 & sp_reg_out4 [3:0] $end
$var wire 4 ' sp_reg_out3 [3:0] $end
$var wire 4 ( sp_reg_out2 [3:0] $end
$var wire 4 ) sp_reg_out1 [3:0] $end
$var wire 4 * reg_out8 [3:0] $end
$var wire 4 + reg_out7 [3:0] $end
$var wire 4 , reg_out6 [3:0] $end
$var wire 4 - reg_out5 [3:0] $end
$var wire 4 . reg_out4 [3:0] $end
$var wire 4 / reg_out3 [3:0] $end
$var wire 4 0 reg_out2 [3:0] $end
$var wire 4 1 reg_out1 [3:0] $end
$var wire 1 2 qbar7_ui $end
$var wire 1 3 qbar7_sp $end
$var wire 1 4 qbar6_ui $end
$var wire 1 5 qbar6_sp $end
$var wire 1 6 qbar5_ui $end
$var wire 1 7 qbar5_sp $end
$var wire 1 8 qbar4_ui $end
$var wire 1 9 qbar4_sp $end
$var wire 1 : qbar3_ui $end
$var wire 1 ; qbar3_sp $end
$var wire 1 < qbar2_ui $end
$var wire 1 = qbar2_sp $end
$var wire 1 > qbar1_ui $end
$var wire 1 ? qbar1_sp $end
$var wire 1 @ q7_ui $end
$var wire 1 A q7_sp $end
$var wire 1 B q6_ui $end
$var wire 1 C q6_sp $end
$var wire 1 D q5_ui $end
$var wire 1 E q5_sp $end
$var wire 1 F q4_ui $end
$var wire 1 G q4_sp $end
$var wire 1 H q3_ui $end
$var wire 1 I q3_sp $end
$var wire 1 J q2_ui $end
$var wire 1 K q2_sp $end
$var wire 1 L q1_ui $end
$var wire 1 M q1_sp $end
$var wire 5 N out [4:0] $end
$var wire 2 O mode_out [1:0] $end
$var wire 1 P comp_out $end
$var wire 4 Q attempt_count [3:0] $end
$var wire 1 R alarm_not_on $end
$var wire 1 S alarm $end
$var reg 1 T rst_alarm $end
$var reg 1 U rst_attempts $end
$var reg 1 V rst_sp $end
$var reg 1 W rst_ui $end
$var reg 1 X sel $end
$var reg 1 Y t $end
$var reg 10 Z x [9:0] $end
$scope module attempts $end
$var wire 1 U reset $end
$var wire 1 2 clk $end
$var reg 4 [ count [3:0] $end
$upscope $end
$scope module comp_circ $end
$var wire 32 \ in_1 [31:0] $end
$var wire 32 ] in_2 [31:0] $end
$var wire 1 P eq $end
$upscope $end
$scope module dmx $end
$var wire 1 ^ Press_in $end
$var wire 1 X select $end
$var reg 2 _ Mode_out [1:0] $end
$upscope $end
$scope module enc $end
$var wire 10 ` D_in [9:0] $end
$var reg 5 a BCD_out [4:0] $end
$upscope $end
$scope module input_array $end
$var wire 1 W clear $end
$var wire 4 b reg_in1 [3:0] $end
$var wire 4 c reg_in2 [3:0] $end
$var wire 4 d reg_in3 [3:0] $end
$var wire 4 e reg_in4 [3:0] $end
$var wire 4 f reg_in5 [3:0] $end
$var wire 4 g reg_in6 [3:0] $end
$var wire 4 h reg_in7 [3:0] $end
$var wire 4 i reg_in8 [3:0] $end
$var wire 2 j reg_mode [1:0] $end
$var wire 4 k reg_out8 [3:0] $end
$var wire 4 l reg_out7 [3:0] $end
$var wire 4 m reg_out6 [3:0] $end
$var wire 4 n reg_out5 [3:0] $end
$var wire 4 o reg_out4 [3:0] $end
$var wire 4 p reg_out3 [3:0] $end
$var wire 4 q reg_out2 [3:0] $end
$var wire 4 r reg_out1 [3:0] $end
$var wire 1 2 clk8 $end
$var wire 1 6 clk7 $end
$var wire 1 4 clk6 $end
$var wire 1 8 clk5 $end
$var wire 1 @ clk4 $end
$var wire 1 D clk3 $end
$var wire 1 B clk2 $end
$var wire 1 F clk1 $end
$scope module reg1 $end
$var wire 4 s reg_in [3:0] $end
$var wire 2 t reg_mode [1:0] $end
$var wire 1 W reset $end
$var wire 1 F clock $end
$var reg 4 u reg_out [3:0] $end
$upscope $end
$scope module reg2 $end
$var wire 4 v reg_in [3:0] $end
$var wire 2 w reg_mode [1:0] $end
$var wire 1 W reset $end
$var wire 1 B clock $end
$var reg 4 x reg_out [3:0] $end
$upscope $end
$scope module reg3 $end
$var wire 4 y reg_in [3:0] $end
$var wire 2 z reg_mode [1:0] $end
$var wire 1 W reset $end
$var wire 1 D clock $end
$var reg 4 { reg_out [3:0] $end
$upscope $end
$scope module reg4 $end
$var wire 4 | reg_in [3:0] $end
$var wire 2 } reg_mode [1:0] $end
$var wire 1 W reset $end
$var wire 1 @ clock $end
$var reg 4 ~ reg_out [3:0] $end
$upscope $end
$scope module reg5 $end
$var wire 4 !" reg_in [3:0] $end
$var wire 2 "" reg_mode [1:0] $end
$var wire 1 W reset $end
$var wire 1 8 clock $end
$var reg 4 #" reg_out [3:0] $end
$upscope $end
$scope module reg6 $end
$var wire 4 $" reg_in [3:0] $end
$var wire 2 %" reg_mode [1:0] $end
$var wire 1 W reset $end
$var wire 1 4 clock $end
$var reg 4 &" reg_out [3:0] $end
$upscope $end
$scope module reg7 $end
$var wire 4 '" reg_in [3:0] $end
$var wire 2 (" reg_mode [1:0] $end
$var wire 1 W reset $end
$var wire 1 6 clock $end
$var reg 4 )" reg_out [3:0] $end
$upscope $end
$scope module reg8 $end
$var wire 4 *" reg_in [3:0] $end
$var wire 2 +" reg_mode [1:0] $end
$var wire 1 W reset $end
$var wire 1 2 clock $end
$var reg 4 ," reg_out [3:0] $end
$upscope $end
$upscope $end
$scope module input_array_2 $end
$var wire 1 V clear $end
$var wire 4 -" reg_in1 [3:0] $end
$var wire 4 ." reg_in2 [3:0] $end
$var wire 4 /" reg_in3 [3:0] $end
$var wire 4 0" reg_in4 [3:0] $end
$var wire 4 1" reg_in5 [3:0] $end
$var wire 4 2" reg_in6 [3:0] $end
$var wire 4 3" reg_in7 [3:0] $end
$var wire 4 4" reg_in8 [3:0] $end
$var wire 2 5" reg_mode [1:0] $end
$var wire 4 6" reg_out8 [3:0] $end
$var wire 4 7" reg_out7 [3:0] $end
$var wire 4 8" reg_out6 [3:0] $end
$var wire 4 9" reg_out5 [3:0] $end
$var wire 4 :" reg_out4 [3:0] $end
$var wire 4 ;" reg_out3 [3:0] $end
$var wire 4 <" reg_out2 [3:0] $end
$var wire 4 =" reg_out1 [3:0] $end
$var wire 1 3 clk8 $end
$var wire 1 7 clk7 $end
$var wire 1 5 clk6 $end
$var wire 1 9 clk5 $end
$var wire 1 A clk4 $end
$var wire 1 E clk3 $end
$var wire 1 C clk2 $end
$var wire 1 G clk1 $end
$scope module reg1 $end
$var wire 4 >" reg_in [3:0] $end
$var wire 2 ?" reg_mode [1:0] $end
$var wire 1 V reset $end
$var wire 1 G clock $end
$var reg 4 @" reg_out [3:0] $end
$upscope $end
$scope module reg2 $end
$var wire 4 A" reg_in [3:0] $end
$var wire 2 B" reg_mode [1:0] $end
$var wire 1 V reset $end
$var wire 1 C clock $end
$var reg 4 C" reg_out [3:0] $end
$upscope $end
$scope module reg3 $end
$var wire 4 D" reg_in [3:0] $end
$var wire 2 E" reg_mode [1:0] $end
$var wire 1 V reset $end
$var wire 1 E clock $end
$var reg 4 F" reg_out [3:0] $end
$upscope $end
$scope module reg4 $end
$var wire 4 G" reg_in [3:0] $end
$var wire 2 H" reg_mode [1:0] $end
$var wire 1 V reset $end
$var wire 1 A clock $end
$var reg 4 I" reg_out [3:0] $end
$upscope $end
$scope module reg5 $end
$var wire 4 J" reg_in [3:0] $end
$var wire 2 K" reg_mode [1:0] $end
$var wire 1 V reset $end
$var wire 1 9 clock $end
$var reg 4 L" reg_out [3:0] $end
$upscope $end
$scope module reg6 $end
$var wire 4 M" reg_in [3:0] $end
$var wire 2 N" reg_mode [1:0] $end
$var wire 1 V reset $end
$var wire 1 5 clock $end
$var reg 4 O" reg_out [3:0] $end
$upscope $end
$scope module reg7 $end
$var wire 4 P" reg_in [3:0] $end
$var wire 2 Q" reg_mode [1:0] $end
$var wire 1 V reset $end
$var wire 1 7 clock $end
$var reg 4 R" reg_out [3:0] $end
$upscope $end
$scope module reg8 $end
$var wire 4 S" reg_in [3:0] $end
$var wire 2 T" reg_mode [1:0] $end
$var wire 1 V reset $end
$var wire 1 3 clock $end
$var reg 4 U" reg_out [3:0] $end
$upscope $end
$upscope $end
$scope module input_t_ff $end
$var wire 1 V" clk $end
$var wire 1 L q1 $end
$var wire 1 J q2 $end
$var wire 1 H q3 $end
$var wire 1 > qbar1 $end
$var wire 1 < qbar2 $end
$var wire 1 : qbar3 $end
$var wire 1 W rst $end
$var wire 1 Y t $end
$var wire 1 W" t3_qbar $end
$var wire 1 X" t3_q $end
$var wire 1 Y" t2_qbar $end
$var wire 1 Z" t2_q $end
$var wire 1 [" t1_qbar $end
$var wire 1 \" t1_q $end
$var wire 1 2 qbar7 $end
$var wire 1 4 qbar6 $end
$var wire 1 6 qbar5 $end
$var wire 1 8 qbar4 $end
$var wire 1 @ q7 $end
$var wire 1 B q6 $end
$var wire 1 D q5 $end
$var wire 1 F q4 $end
$scope module t1 $end
$var wire 1 V" clk $end
$var wire 1 [" qbar $end
$var wire 1 W rst $end
$var wire 1 Y t $end
$var reg 1 \" q $end
$upscope $end
$scope module t2 $end
$var wire 1 \" clk $end
$var wire 1 Y" qbar $end
$var wire 1 W rst $end
$var wire 1 Y t $end
$var reg 1 Z" q $end
$upscope $end
$scope module t3 $end
$var wire 1 [" clk $end
$var wire 1 W" qbar $end
$var wire 1 W rst $end
$var wire 1 Y t $end
$var reg 1 X" q $end
$upscope $end
$scope module t4 $end
$var wire 1 Z" clk $end
$var wire 1 8 qbar $end
$var wire 1 W rst $end
$var wire 1 Y t $end
$var reg 1 F q $end
$upscope $end
$scope module t5 $end
$var wire 1 Y" clk $end
$var wire 1 6 qbar $end
$var wire 1 W rst $end
$var wire 1 Y t $end
$var reg 1 D q $end
$upscope $end
$scope module t6 $end
$var wire 1 X" clk $end
$var wire 1 4 qbar $end
$var wire 1 W rst $end
$var wire 1 Y t $end
$var reg 1 B q $end
$upscope $end
$scope module t7 $end
$var wire 1 W" clk $end
$var wire 1 2 qbar $end
$var wire 1 W rst $end
$var wire 1 Y t $end
$var reg 1 @ q $end
$upscope $end
$upscope $end
$scope module input_t_ff_2 $end
$var wire 1 ]" clk $end
$var wire 1 M q1 $end
$var wire 1 K q2 $end
$var wire 1 I q3 $end
$var wire 1 ? qbar1 $end
$var wire 1 = qbar2 $end
$var wire 1 ; qbar3 $end
$var wire 1 V rst $end
$var wire 1 Y t $end
$var wire 1 ^" t3_qbar $end
$var wire 1 _" t3_q $end
$var wire 1 `" t2_qbar $end
$var wire 1 a" t2_q $end
$var wire 1 b" t1_qbar $end
$var wire 1 c" t1_q $end
$var wire 1 3 qbar7 $end
$var wire 1 5 qbar6 $end
$var wire 1 7 qbar5 $end
$var wire 1 9 qbar4 $end
$var wire 1 A q7 $end
$var wire 1 C q6 $end
$var wire 1 E q5 $end
$var wire 1 G q4 $end
$scope module t1 $end
$var wire 1 ]" clk $end
$var wire 1 b" qbar $end
$var wire 1 V rst $end
$var wire 1 Y t $end
$var reg 1 c" q $end
$upscope $end
$scope module t2 $end
$var wire 1 c" clk $end
$var wire 1 `" qbar $end
$var wire 1 V rst $end
$var wire 1 Y t $end
$var reg 1 a" q $end
$upscope $end
$scope module t3 $end
$var wire 1 b" clk $end
$var wire 1 ^" qbar $end
$var wire 1 V rst $end
$var wire 1 Y t $end
$var reg 1 _" q $end
$upscope $end
$scope module t4 $end
$var wire 1 a" clk $end
$var wire 1 9 qbar $end
$var wire 1 V rst $end
$var wire 1 Y t $end
$var reg 1 G q $end
$upscope $end
$scope module t5 $end
$var wire 1 `" clk $end
$var wire 1 7 qbar $end
$var wire 1 V rst $end
$var wire 1 Y t $end
$var reg 1 E q $end
$upscope $end
$scope module t6 $end
$var wire 1 _" clk $end
$var wire 1 5 qbar $end
$var wire 1 V rst $end
$var wire 1 Y t $end
$var reg 1 C q $end
$upscope $end
$scope module t7 $end
$var wire 1 ^" clk $end
$var wire 1 3 qbar $end
$var wire 1 V rst $end
$var wire 1 Y t $end
$var reg 1 A q $end
$upscope $end
$upscope $end
$scope module out_circ $end
$var wire 1 d" bit_0 $end
$var wire 1 e" bit_2 $end
$var wire 1 P is_equal $end
$var wire 1 T reset_alarm $end
$var wire 1 ! unlocked $end
$var wire 1 f" w1 $end
$var wire 1 g" w2 $end
$var wire 1 R qbar $end
$var wire 1 S alarm $end
$scope module d1 $end
$var wire 1 g" clk $end
$var wire 1 g" d $end
$var wire 1 R qbar $end
$var wire 1 T rst $end
$var reg 1 S q $end
$upscope $end
$upscope $end
$upscope $end
$enddefinitions $end
$comment Show the parameter values. $end
$dumpall
$end
#0
$dumpvars
0g"
0f"
0e"
0d"
0c"
1b"
0a"
1`"
0_"
1^"
0]"
0\"
1["
0Z"
1Y"
0X"
1W"
0V"
b0 U"
b11 T"
b0 S"
b0 R"
b11 Q"
b0 P"
b0 O"
b11 N"
b0 M"
b0 L"
b11 K"
b0 J"
b0 I"
b11 H"
b0 G"
b0 F"
b11 E"
b0 D"
b0 C"
b11 B"
b0 A"
b0 @"
b11 ?"
b0 >"
b0 ="
b0 <"
b0 ;"
b0 :"
b0 9"
b0 8"
b0 7"
b0 6"
b11 5"
b0 4"
b0 3"
b0 2"
b0 1"
b0 0"
b0 /"
b0 ."
b0 -"
b0 ,"
b11 +"
b0 *"
b0 )"
b11 ("
b0 '"
b0 &"
b11 %"
b0 $"
b0 #"
b11 ""
b0 !"
b0 ~
b11 }
b0 |
b0 {
b11 z
b0 y
b0 x
b11 w
b0 v
b0 u
b11 t
b0 s
b0 r
b0 q
b0 p
b0 o
b0 n
b0 m
b0 l
b0 k
b11 j
b0 i
b0 h
b0 g
b0 f
b0 e
b0 d
b0 c
b0 b
b0 a
b0 `
b0 _
0^
b0 ]
b0 \
b0 [
b0 Z
0Y
0X
1W
1V
1U
1T
xS
xR
b0 Q
1P
b0 O
b0 N
0M
0L
0K
0J
0I
0H
0G
0F
0E
0D
0C
0B
0A
0@
1?
1>
1=
1<
1;
1:
19
18
17
16
15
14
13
12
b0 1
b0 0
b0 /
b0 .
b0 -
b0 ,
b0 +
b0 *
b0 )
b0 (
b0 '
b0 &
b0 %
b0 $
b0 #
b0 "
x!
$end
#1
1Y
0W
0V
0U
0T
#5
1f"
0!
0P
b100000000000000000000000000000 \
b10 1
b10 r
b10 u
08
1F
0<
0Y"
1J
1Z"
0>
0["
1L
1\"
1V"
b1 O
b1 _
b10 4"
b10 S"
b10 3"
b10 P"
b10 2"
b10 M"
b10 1"
b10 J"
b10 0"
b10 G"
b10 /"
b10 D"
b10 ."
b10 A"
b10 -"
b10 >"
b10 i
b10 *"
b10 h
b10 '"
b10 g
b10 $"
b10 f
b10 !"
b10 e
b10 |
b10 d
b10 y
b10 c
b10 v
b10 b
b10 s
1^
b10010 N
b10010 a
b100 Z
b100 `
#10
0V"
b0 O
b0 _
b0 4"
b0 S"
b0 3"
b0 P"
b0 2"
b0 M"
b0 1"
b0 J"
b0 0"
b0 G"
b0 /"
b0 D"
b0 ."
b0 A"
b0 -"
b0 >"
b0 i
b0 *"
b0 h
b0 '"
b0 g
b0 $"
b0 f
b0 !"
b0 e
b0 |
b0 d
b0 y
b0 c
b0 v
b0 b
b0 s
0^
b0 N
b0 a
b0 Z
b0 `
#15
b100001000000000000000000000000 \
b1 0
b1 q
b1 x
04
1B
0:
0W"
1H
1X"
1>
1["
0L
0\"
1V"
b1 O
b1 _
b1 4"
b1 S"
b1 3"
b1 P"
b1 2"
b1 M"
b1 1"
b1 J"
b1 0"
b1 G"
b1 /"
b1 D"
b1 ."
b1 A"
b1 -"
b1 >"
b1 i
b1 *"
b1 h
b1 '"
b1 g
b1 $"
b1 f
b1 !"
b1 e
b1 |
b1 d
b1 y
b1 c
b1 v
b1 b
b1 s
1^
b10001 N
b10001 a
b10 Z
b10 `
#20
0V"
b0 O
b0 _
b0 4"
b0 S"
b0 3"
b0 P"
b0 2"
b0 M"
b0 1"
b0 J"
b0 0"
b0 G"
b0 /"
b0 D"
b0 ."
b0 A"
b0 -"
b0 >"
b0 i
b0 *"
b0 h
b0 '"
b0 g
b0 $"
b0 f
b0 !"
b0 e
b0 |
b0 d
b0 y
b0 c
b0 v
b0 b
b0 s
0^
b0 N
b0 a
b0 Z
b0 `
#25
b100001100100000000000000000000 \
b1001 /
b1001 p
b1001 {
06
1D
1<
1Y"
0J
0Z"
0>
0["
1L
1\"
1V"
b1 O
b1 _
b1001 4"
b1001 S"
b1001 3"
b1001 P"
b1001 2"
b1001 M"
b1001 1"
b1001 J"
b1001 0"
b1001 G"
b1001 /"
b1001 D"
b1001 ."
b1001 A"
b1001 -"
b1001 >"
b1001 i
b1001 *"
b1001 h
b1001 '"
b1001 g
b1001 $"
b1001 f
b1001 !"
b1001 e
b1001 |
b1001 d
b1001 y
b1001 c
b1001 v
b1001 b
b1001 s
1^
b11001 N
b11001 a
b1000000000 Z
b1000000000 `
#30
0V"
b0 O
b0 _
b0 4"
b0 S"
b0 3"
b0 P"
b0 2"
b0 M"
b0 1"
b0 J"
b0 0"
b0 G"
b0 /"
b0 D"
b0 ."
b0 A"
b0 -"
b0 >"
b0 i
b0 *"
b0 h
b0 '"
b0 g
b0 $"
b0 f
b0 !"
b0 e
b0 |
b0 d
b0 y
b0 c
b0 v
b0 b
b0 s
0^
b0 N
b0 a
b0 Z
b0 `
