desc_lib.v
// Design of encoder for inputs ~ makes use of Behavioural Description
module input_encoder (input [9:0] D_in, output reg [4:0] BCD_out);

    always @(D_in) begin
        casez (D_in)
            10'b0000000001: BCD_out = 5'b10000;  // D_in[0]
            10'b000000001?: BCD_out = 5'b10001;  // D_in[1]
            10'b00000001??: BCD_out = 5'b10010;  // D_in[2]
            10'b0000001???: BCD_out = 5'b10011;  // D_in[3]
            10'b000001????: BCD_out = 5'b10100;  // D_in[4]
            10'b00001?????: BCD_out = 5'b10101;  // D_in[5]
            10'b0001??????: BCD_out = 5'b10110;  // D_in[6]
            10'b001???????: BCD_out = 5'b10111;  // D_in[7]
            10'b01????????: BCD_out = 5'b11000;  // D_in[8]
            10'b1?????????: BCD_out = 5'b11001;  // D_in[9]
            default: BCD_out = 5'b00000;  // Default case to handle no-input states
        endcase

    end

endmodule

// Design of 1-2 Demultiplexer for clocking T flip-flops - makes use of Behavioural Description
module demux1_2 (output reg [1:0] Mode_out, input Press_in, input select);

    always @(Press_in, select) begin
        Mode_out = 2'b00;
        case (select)
            1'b0: Mode_out[0] = Press_in;
            1'b1: Mode_out[1] = Press_in;
            default: Mode_out = 2'b00;
        endcase
    end

endmodule

// Design of a T flipflops for clocking the memory for inputs sequentially - makes use of Behavioural Description
module t_ff (output reg q, output qbar, input clk, rst, t);

	assign qbar = ~q;

	always @(posedge clk)
	begin
		if (rst)
			q <= 0;
		else
			case(t)
				1'b0: q <= q;
				1'b1: q <= ~q;
			endcase
	end

    always @(negedge clk)
    begin
        if (rst)
			q <= 0;
    end
endmodule

// Design of a T-FF circuit ~ makes use of Gate-Level Modelling
module t_ff_circuit (output wire q1, q2, q3, qbar1, qbar2, qbar3, input clk, rst, t);

    wire t1_q, t1_qbar;
    
    t_ff t1 (t1_q, t1_qbar, clk, rst, t);
    
    t_ff t2 (q2, qbar2, t1_q, rst, t);

    t_ff t3 (q3, qbar3, t1_qbar, rst, t);
    
    assign q1 = t1_q;
    assign qbar1 = t1_qbar;

endmodule

module univ_shift_reg (output reg [3:0] reg_out, input clock, reset, input [1:0] reg_mode, input [3:0] reg_in);

  always @(posedge clock)
  begin
    if(reset)
      reg_out <= 0;
    else
      begin
        case(reg_mode)
          2'b00 : reg_out <= reg_out;      // locked mode, do nothing
          2'b01 : reg_out <= {reg_in[0], reg_out[3:1]};//reg_out >> 1; // RFSR
          2'b10 : reg_out <= {reg_out[2:0], reg_in[0]};//reg_out << 1; // LFSR
          2'b11 : reg_out <= reg_in;       // parallel in parallel out
        endcase
      end
  end

  always @(negedge clock)
  begin
    if(reset)
        reg_out <= 0;
  end
  
endmodule

module shift_reg_array (input clk1, clk2, clk3, clk4, clear,
    input [3:0] reg_in1, input [3:0] reg_in2, input [3:0] reg_in3, input [3:0] reg_in4, input [1:0] reg_mode, 
    output [3:0] reg_out1, output [3:0] reg_out2, output [3:0] reg_out3, output [3:0] reg_out4);

    univ_shift_reg reg1(reg_out1, clk1, clear, reg_mode, reg_in1);
    univ_shift_reg reg2(reg_out2, clk2, clear, reg_mode, reg_in2);
    univ_shift_reg reg3(reg_out3, clk3, clear, reg_mode, reg_in3);
    univ_shift_reg reg4(reg_out4, clk4, clear, reg_mode, reg_in4);

endmodule

main_tb.v
`timescale 1 ns / 1 ns
`include "desc_lib.v"

module main_tb;

    wire [4:0] out;
    wire [1:0] mode_out;
    wire [3:0] reg_out1, reg_out2, reg_out3, reg_out4;
    reg [9:0] x;
    reg sel, rst_ui, t;
    wire q1_ui, q2_ui, q3_ui, qbar1_ui, qbar2_ui, qbar3_ui;

    input_encoder enc(x, out);
    demux1_2 dmx(mode_out, out[4], sel);
    t_ff_circuit input_t_ff(q1_ui, q2_ui, q3_ui, qbar1_ui, qbar2_ui, qbar3_ui, mode_out[0], rst_ui, t);
    shift_reg_array input_array(q2_ui, q3_ui, qbar2_ui, qbar3_ui, rst_ui, out[3:0], out[3:0], out[3:0], out[3:0], 2'b11,
        reg_out1, reg_out2, reg_out3, reg_out4);

    /*
    initial begin
        clk = 0;
        forever #5 clk = ~clk;
    end
    */

    initial begin
        $dumpfile("main_tb.vcd"); $dumpvars(0, main_tb);

        $display("*** SIMULATING INPUT ENCODER ***");
        $display("\t BCD Output\t   Keypad Input\t    Demux Output\t\t     TFF Output\t\t\t\t\t       Shift Register Output");
        $monitor("\t   %b\t    %b\t         %b\t\t     clk1=%b, clk2=%b, clk3=%b, clk4=%b\t\t       SR1=%b, SR2=%b, SR3=%b, SR4=%b", out, x, mode_out, q2_ui, q3_ui, qbar2_ui, qbar3_ui, reg_out1, reg_out2, reg_out3, reg_out4);

        x[0]=0; x[1]=0; x[2]=0; x[3]=0; x[4]=0; 
        x[5]=0; x[6]=0; x[7]=0; x[8]=0; x[9]=0;

        sel = 0;
        t = 0;
        rst_ui = 1;
        
        
        #1 t = 1;
        #1 rst_ui = 0;
        #5 x[2]=1;
        #5 x[2]=0;
        #5 x[1]=1;
        #5 x[1]=0;
        #5 x[9]=1;
        #5 x[9]=0;
        #5 x[7]=1;
        #5 x[7]=0;
        #20 $finish;

    end


endmodule

main_tb.vcd
$date
	Tue Jul 16 14:20:57 2024
$end
$version
	Icarus Verilog
$end
$timescale
	1ns
$end
$scope module main_tb $end
$var wire 4 ! reg_out4 [3:0] $end
$var wire 4 " reg_out3 [3:0] $end
$var wire 4 # reg_out2 [3:0] $end
$var wire 4 $ reg_out1 [3:0] $end
$var wire 1 % qbar3_ui $end
$var wire 1 & qbar2_ui $end
$var wire 1 ' qbar1_ui $end
$var wire 1 ( q3_ui $end
$var wire 1 ) q2_ui $end
$var wire 1 * q1_ui $end
$var wire 5 + out [4:0] $end
$var wire 2 , mode_out [1:0] $end
$var reg 1 - rst_ui $end
$var reg 1 . sel $end
$var reg 1 / t $end
$var reg 10 0 x [9:0] $end
$scope module dmx $end
$var wire 1 1 Press_in $end
$var wire 1 . select $end
$var reg 2 2 Mode_out [1:0] $end
$upscope $end
$scope module enc $end
$var wire 10 3 D_in [9:0] $end
$var reg 5 4 BCD_out [4:0] $end
$upscope $end
$scope module input_array $end
$var wire 1 - clear $end
$var wire 4 5 reg_in1 [3:0] $end
$var wire 4 6 reg_in2 [3:0] $end
$var wire 4 7 reg_in3 [3:0] $end
$var wire 4 8 reg_in4 [3:0] $end
$var wire 2 9 reg_mode [1:0] $end
$var wire 4 : reg_out4 [3:0] $end
$var wire 4 ; reg_out3 [3:0] $end
$var wire 4 < reg_out2 [3:0] $end
$var wire 4 = reg_out1 [3:0] $end
$var wire 1 % clk4 $end
$var wire 1 & clk3 $end
$var wire 1 ( clk2 $end
$var wire 1 ) clk1 $end
$scope module reg1 $end
$var wire 4 > reg_in [3:0] $end
$var wire 2 ? reg_mode [1:0] $end
$var wire 1 - reset $end
$var wire 1 ) clock $end
$var reg 4 @ reg_out [3:0] $end
$upscope $end
$scope module reg2 $end
$var wire 4 A reg_in [3:0] $end
$var wire 2 B reg_mode [1:0] $end
$var wire 1 - reset $end
$var wire 1 ( clock $end
$var reg 4 C reg_out [3:0] $end
$upscope $end
$scope module reg3 $end
$var wire 4 D reg_in [3:0] $end
$var wire 2 E reg_mode [1:0] $end
$var wire 1 - reset $end
$var wire 1 & clock $end
$var reg 4 F reg_out [3:0] $end
$upscope $end
$scope module reg4 $end
$var wire 4 G reg_in [3:0] $end
$var wire 2 H reg_mode [1:0] $end
$var wire 1 - reset $end
$var wire 1 % clock $end
$var reg 4 I reg_out [3:0] $end
$upscope $end
$upscope $end
$scope module input_t_ff $end
$var wire 1 J clk $end
$var wire 1 * q1 $end
$var wire 1 ' qbar1 $end
$var wire 1 - rst $end
$var wire 1 / t $end
$var wire 1 K t1_qbar $end
$var wire 1 L t1_q $end
$var wire 1 % qbar3 $end
$var wire 1 & qbar2 $end
$var wire 1 ( q3 $end
$var wire 1 ) q2 $end
$scope module t1 $end
$var wire 1 J clk $end
$var wire 1 K qbar $end
$var wire 1 - rst $end
$var wire 1 / t $end
$var reg 1 L q $end
$upscope $end
$scope module t2 $end
$var wire 1 L clk $end
$var wire 1 & qbar $end
$var wire 1 - rst $end
$var wire 1 / t $end
$var reg 1 ) q $end
$upscope $end
$scope module t3 $end
$var wire 1 K clk $end
$var wire 1 % qbar $end
$var wire 1 - rst $end
$var wire 1 / t $end
$var reg 1 ( q $end
$upscope $end
$upscope $end
$upscope $end
$enddefinitions $end
$comment Show the parameter values. $end
$dumpall
$end
#0
$dumpvars
0L
1K
0J
b0 I
b11 H
b0 G
b0 F
b11 E
b0 D
b0 C
b11 B
b0 A
b0 @
b11 ?
b0 >
b0 =
b0 <
b0 ;
b0 :
b11 9
b0 8
b0 7
b0 6
b0 5
b0 4
b0 3
b0 2
01
b0 0
0/
0.
1-
b0 ,
b0 +
0*
0)
0(
1'
1&
1%
b0 $
b0 #
b0 "
b0 !
$end
#1
1/
#2
0-
#7
b10 $
b10 =
b10 @
0&
1)
0'
0K
1*
1L
1J
b1 ,
b1 2
b10 8
b10 G
b10 7
b10 D
b10 6
b10 A
b10 5
b10 >
11
b10010 +
b10010 4
b100 0
b100 3
#12
0J
b0 ,
b0 2
b0 8
b0 G
b0 7
b0 D
b0 6
b0 A
b0 5
b0 >
01
b0 +
b0 4
b0 0
b0 3
#17
b1 #
b1 <
b1 C
0%
1(
1'
1K
0*
0L
1J
b1 ,
b1 2
b1 8
b1 G
b1 7
b1 D
b1 6
b1 A
b1 5
b1 >
11
b10001 +
b10001 4
b10 0
b10 3
#22
0J
b0 ,
b0 2
b0 8
b0 G
b0 7
b0 D
b0 6
b0 A
b0 5
b0 >
01
b0 +
b0 4
b0 0
b0 3
#27
b1001 "
b1001 ;
b1001 F
1&
0)
0'
0K
1*
1L
1J
b1 ,
b1 2
b1001 8
b1001 G
b1001 7
b1001 D
b1001 6
b1001 A
b1001 5
b1001 >
11
b11001 +
b11001 4
b1000000000 0
b1000000000 3
#32
0J
b0 ,
b0 2
b0 8
b0 G
b0 7
b0 D
b0 6
b0 A
b0 5
b0 >
01
b0 +
b0 4
b0 0
b0 3
#37
b111 !
b111 :
b111 I
1%
0(
1'
1K
0*
0L
1J
b1 ,
b1 2
b111 8
b111 G
b111 7
b111 D
b111 6
b111 A
b111 5
b111 >
11
b10111 +
b10111 4
b10000000 0
b10000000 3
#42
0J
b0 ,
b0 2
b0 8
b0 G
b0 7
b0 D
b0 6
b0 A
b0 5
b0 >
01
b0 +
b0 4
b0 0
b0 3
